Workbook
Name _Int_h0KAy7bb: '2a. Administration'!$B$9
Name _Int_h0KAy7bb: '2b. Planning'!$B$7
Name _Int_h0KAy7bb: '2c. Delivery'!$B$9
Name _Int_h0KAy7bb: '2d. Reconciliation'!$B$9
Name _Int_h0KAy7bb: '2e. Reporting'!$B$9
Name _Int_h0KAy7bb: '3a. Security'!#REF!
Name _Int_h0KAy7bb: '3b. User Interface and User Exp'!#REF!
Name _Int_h0KAy7bb: '3c. Performance-Scalability'!#REF!
Name _Int_h0KAy7bb: '3d. Support-Maintenance'!#REF!
Name _Int_h0KAy7bb: '3e. Reliability-Availability'!#REF!
Name _Int_h0KAy7bb: '3f. Integration'!#REF!
Name _Int_h0KAy7bb: '3g. Configurability'!#REF!
Name _Int_h0KAy7bb: '3h. Compliance'!#REF!
Name _Int_QiuZ3ikt: '2b. Planning'!$C$24
Name _Int_QiuZ3ikt: '2c. Delivery'!$C$33
Name _Int_QiuZ3ikt: '2d. Reconciliation'!#REF!
Name _Int_QiuZ3ikt: '2e. Reporting'!#REF!
Name _Int_QiuZ3ikt: '3a. Security'!#REF!
Name _Int_QiuZ3ikt: '3b. User Interface and User Exp'!#REF!
Name _Int_QiuZ3ikt: '3c. Performance-Scalability'!#REF!
Name _Int_QiuZ3ikt: '3d. Support-Maintenance'!#REF!
Name _Int_QiuZ3ikt: '3e. Reliability-Availability'!#REF!
Name _Int_QiuZ3ikt: '3f. Integration'!#REF!
Name _Int_QiuZ3ikt: '3g. Configurability'!#REF!
Name _Int_QiuZ3ikt: '3h. Compliance'!#REF!

Sheet Summary
A1: Requirements | C1: SX | D1: X | F1: SX | G1: X
A2: # | B2: Item | C2: Critical | D2: Non Critical | E2: Total | F2: Critical | G2: Non Critical | H2: Total | I2: Delta
A3: 2a | B3: Administration | C3: =COUNTIFS('2a. Administration'!$I:$I,Summary!$A3,'2a. Administration'!$E:$E,Summary!C1) -> 68 | D3: =COUNTIFS('2a. Administration'!$I:$I,Summary!$A3,'2a. Administration'!$E:$E,Summary!D1) -> 19 | E3: =SUM(C3:D3) -> 87 | F3: =COUNTIFS('2a. Administration'!$I:$I,Summary!$A3,'2a. Administration'!$G:$G,Summary!F1) -> 49 | G3: =COUNTIFS('2a. Administration'!$I:$I,Summary!$A3,'2a. Administration'!$G:$G,Summary!G1) -> 8 | H3: =SUM(F3:G3) -> 57 | I3: =H3-E3 -> -30
A4: 2b | B4: Planning | C4: =COUNTIFS('2b. Planning'!$I:$I,Summary!$A4,'2b. Planning'!$E:$E,Summary!C1) -> 155 | D4: =COUNTIFS('2b. Planning'!$I:$I,Summary!$A4,'2b. Planning'!$E:$E,Summary!D1) -> 97 | E4: =SUM(C4:D4) -> 252 | F4: =COUNTIFS('2b. Planning'!$I:$I,Summary!$A4,'2b. Planning'!$G:$G,Summary!F1) -> 118 | G4: =COUNTIFS('2b. Planning'!$I:$I,Summary!$A4,'2b. Planning'!$G:$G,Summary!G1) -> 44 | H4: =SUM(F4:G4) -> 162 | I4: =H4-E4 -> -90
A5: 2c | B5: Delivery | C5: =COUNTIFS('2c. Delivery'!$I:$I,Summary!$A5,'2c. Delivery'!$E:$E,Summary!C1) -> 27 | D5: =COUNTIFS('2c. Delivery'!$I:$I,Summary!$A5,'2c. Delivery'!$E:$E,Summary!D1) -> 74 | E5: =SUM(C5:D5) -> 101 | F5: =COUNTIFS('2c. Delivery'!$I:$I,Summary!$A5,'2c. Delivery'!$G:$G,Summary!F1) -> 21 | G5: =COUNTIFS('2c. Delivery'!$I:$I,Summary!$A5,'2c. Delivery'!$G:$G,Summary!G1) -> 38 | H5: =SUM(F5:G5) -> 59 | I5: =H5-E5 -> -42
A6: 2d | B6: Reconciliation | C6: =COUNTIFS('2d. Reconciliation'!$I:$I,Summary!$A6,'2d. Reconciliation'!$E:$E,Summary!C1) -> 17 | D6: =COUNTIFS('2d. Reconciliation'!$I:$I,Summary!$A6,'2d. Reconciliation'!$E:$E,Summary!D1) -> 13 | E6: =SUM(C6:D6) -> 30 | F6: =COUNTIFS('2d. Reconciliation'!$I:$I,Summary!$A6,'2d. Reconciliation'!$G:$G,Summary!F1) -> 12 | G6: =COUNTIFS('2d. Reconciliation'!$I:$I,Summary!$A6,'2d. Reconciliation'!$G:$G,Summary!G1) -> 7 | H6: =SUM(F6:G6) -> 19 | I6: =H6-E6 -> -11
A7: 2e | B7: Reporting | C7: =COUNTIFS('2e. Reporting'!$I:$I,Summary!$A7,'2e. Reporting'!$E:$E,Summary!C1) -> 49 | D7: =COUNTIFS('2e. Reporting'!$I:$I,Summary!$A7,'2e. Reporting'!$E:$E,Summary!D1) -> 25 | E7: =SUM(C7:D7) -> 74 | F7: =COUNTIFS('2e. Reporting'!$I:$I,Summary!$A7,'2e. Reporting'!$G:$G,Summary!F1) -> 49 | G7: =COUNTIFS('2e. Reporting'!$I:$I,Summary!$A7,'2e. Reporting'!$G:$G,Summary!G1) -> 19 | H7: =SUM(F7:G7) -> 68 | I7: =H7-E7 -> -6
A9: 3a | B9: Security | C9: =COUNTIFS('3a. Security'!$I:$I,Summary!$A9,'3a. Security'!$E:$E,Summary!C1) -> 6 | D9: =COUNTIFS('3a. Security'!$I:$I,Summary!$A9,'3a. Security'!$E:$E,Summary!D1) -> 0 | E9: =SUM(C9:D9) -> 6 | F9: =COUNTIFS('3a. Security'!$I:$I,Summary!$A9,'3a. Security'!$G:$G,Summary!F1) -> 6 | G9: =COUNTIFS('3a. Security'!$I:$I,Summary!$A9,'3a. Security'!$G:$G,Summary!G1) -> 0 | H9: =SUM(F9:G9) -> 6 | I9: =H9-E9 -> 0
A10: 3b | B10: User Interface & User Exp | C10: =COUNTIFS('3b. User Interface and User Exp'!$I:$I,Summary!$A10,'3b. User Interface and User Exp'!$E:$E,Summary!C1) -> 2 | D10: =COUNTIFS('3b. User Interface and User Exp'!$I:$I,Summary!$A10,'3b. User Interface and User Exp'!$E:$E,Summary!D1) -> 5 | E10: =SUM(C10:D10) -> 7 | F10: =COUNTIFS('3b. User Interface and User Exp'!$I:$I,Summary!$A10,'3b. User Interface and User Exp'!$G:$G,Summary!F1) -> 2 | G10: =COUNTIFS('3b. User Interface and User Exp'!$I:$I,Summary!$A10,'3b. User Interface and User Exp'!$G:$G,Summary!G1) -> 5 | H10: =SUM(F10:G10) -> 7 | I10: =H10-E10 -> 0
A11: 3c | B11: Performance & Scalability | C11: =COUNTIFS('3c. Performance-Scalability'!$I:$I,Summary!$A11,'3c. Performance-Scalability'!$E:$E,Summary!C1) -> 0 | D11: =COUNTIFS('3c. Performance-Scalability'!$I:$I,Summary!$A11,'3c. Performance-Scalability'!$E:$E,Summary!D1) -> 6 | E11: =SUM(C11:D11) -> 6 | F11: =COUNTIFS('3c. Performance-Scalability'!$I:$I,Summary!$A11,'3c. Performance-Scalability'!$G:$G,Summary!F1) -> 0 | G11: =COUNTIFS('3c. Performance-Scalability'!$I:$I,Summary!$A11,'3c. Performance-Scalability'!$G:$G,Summary!G1) -> 6 | H11: =SUM(F11:G11) -> 6 | I11: =H11-E11 -> 0
A12: 3d | B12: Support-Maintenance | C12: =COUNTIFS('3d. Support-Maintenance'!$I:$I,Summary!$A12,'3d. Support-Maintenance'!$E:$E,Summary!C1) -> 5 | D12: =COUNTIFS('3d. Support-Maintenance'!$I:$I,Summary!$A12,'3d. Support-Maintenance'!$E:$E,Summary!D1) -> 2 | E12: =SUM(C12:D12) -> 7 | F12: =COUNTIFS('3d. Support-Maintenance'!$I:$I,Summary!$A12,'3d. Support-Maintenance'!$G:$G,Summary!F1) -> 5 | G12: =COUNTIFS('3d. Support-Maintenance'!$I:$I,Summary!$A12,'3d. Support-Maintenance'!$G:$G,Summary!G1) -> 2 | H12: =SUM(F12:G12) -> 7 | I12: =H12-E12 -> 0
A13: 3e | B13: Reliability-Availability | C13: =COUNTIFS('3e. Reliability-Availability'!$I:$I,Summary!$A13,'3e. Reliability-Availability'!$E:$E,Summary!C1) -> 4 | D13: =COUNTIFS('3e. Reliability-Availability'!$I:$I,Summary!$A13,'3e. Reliability-Availability'!$E:$E,Summary!D1) -> 4 | E13: =SUM(C13:D13) -> 8 | F13: =COUNTIFS('3e. Reliability-Availability'!$I:$I,Summary!$A13,'3e. Reliability-Availability'!$G:$G,Summary!F1) -> 4 | G13: =COUNTIFS('3e. Reliability-Availability'!$I:$I,Summary!$A13,'3e. Reliability-Availability'!$G:$G,Summary!G1) -> 4 | H13: =SUM(F13:G13) -> 8 | I13: =H13-E13 -> 0
A14: 3f | B14: Integration | C14: =COUNTIFS('3f. Integration'!$I:$I,Summary!$A14,'3f. Integration'!$E:$E,Summary!C1) -> 12 | D14: =COUNTIFS('3f. Integration'!$I:$I,Summary!$A14,'3f. Integration'!$E:$E,Summary!D1) -> 5 | E14: =SUM(C14:D14) -> 17 | F14: =COUNTIFS('3f. Integration'!$I:$I,Summary!$A14,'3f. Integration'!$G:$G,Summary!F1) -> 12 | G14: =COUNTIFS('3f. Integration'!$I:$I,Summary!$A14,'3f. Integration'!$G:$G,Summary!G1) -> 4 | H14: =SUM(F14:G14) -> 16 | I14: =H14-E14 -> -1
A15: 3g | B15: Configurability | C15: =COUNTIFS('3g. Configurability'!$I:$I,Summary!$A15,'3g. Configurability'!$E:$E,Summary!C1) -> 3 | D15: =COUNTIFS('3g. Configurability'!$I:$I,Summary!$A15,'3g. Configurability'!$E:$E,Summary!D1) -> 1 | E15: =SUM(C15:D15) -> 4 | F15: =COUNTIFS('3g. Configurability'!$I:$I,Summary!$A15,'3g. Configurability'!$G:$G,Summary!F1) -> 3 | G15: =COUNTIFS('3g. Configurability'!$I:$I,Summary!$A15,'3g. Configurability'!$G:$G,Summary!G1) -> 1 | H15: =SUM(F15:G15) -> 4 | I15: =H15-E15 -> 0
A16: 3h | B16: Compliance | C16: =COUNTIFS('3h. Compliance'!$I:$I,Summary!$A16,'3h. Compliance'!$E:$E,Summary!C1) -> 4 | D16: =COUNTIFS('3h. Compliance'!$I:$I,Summary!$A16,'3h. Compliance'!$E:$E,Summary!D1) -> 3 | E16: =SUM(C16:D16) -> 7 | F16: =COUNTIFS('3h. Compliance'!$I:$I,Summary!$A16,'3h. Compliance'!$G:$G,Summary!F1) -> 4 | G16: =COUNTIFS('3h. Compliance'!$I:$I,Summary!$A16,'3h. Compliance'!$G:$G,Summary!G1) -> 3 | H16: =SUM(F16:G16) -> 7 | I16: =H16-E16 -> 0
B17: Total | C17: =SUM(C3:C16) -> 352 | D17: =SUM(D3:D16) -> 254 | E17: =SUM(E3:E16) -> 606 | F17: =SUM(F3:F16) -> 285 | G17: =SUM(G3:G16) -> 141 | H17: =SUM(H3:H16) -> 426 | I17: =SUM(I3:I16) -> -180
C19: Y | D19: N | E19: P | F19: Y | G19: N | H19: P | I19: Y | J19: N | K19: P | L19: Y | M19: N | N19: P | O19: Y | P19: N | Q19: P | R19: Y | S19: N | T19: P | U19: Y | V19: N | W19: P
A20: # | B20: Item | C20: Critical | F20: Non Critical | I20: Total | L20: Critical | O20: Non Critical | R20: Total | U20: Delta
A21: 2a | B21: Administration | C21: =COUNTIFS('2a. Administration'!$I:$I,Summary!$A21,'2a. Administration'!$C:$C,Summary!C$19,'2a. Administration'!$E:$E,Summary!$C$1) -> 68 | D21: =COUNTIFS('2a. Administration'!$I:$I,Summary!$A21,'2a. Administration'!$C:$C,Summary!D$19,'2a. Administration'!$E:$E,Summary!$C$1) -> 0 | E21: =COUNTIFS('2a. Administration'!$I:$I,Summary!$A21,'2a. Administration'!$C:$C,Summary!E$19,'2a. Administration'!$E:$E,Summary!$C$1) -> 0 | F21: =COUNTIFS('2a. Administration'!$I:$I,Summary!$A21,'2a. Administration'!$C:$C,Summary!F$19,'2a. Administration'!$E:$E,Summary!$D$1) -> 16 | G21: =COUNTIFS('2a. Administration'!$I:$I,Summary!$A21,'2a. Administration'!$C:$C,Summary!G$19,'2a. Administration'!$E:$E,Summary!$D$1) -> 0 | H21: =COUNTIFS('2a. Administration'!$I:$I,Summary!$A21,'2a. Administration'!$C:$C,Summary!H$19,'2a. Administration'!$E:$E,Summary!$D$1) -> 3 | I21: =C21+F21 -> 84 | J21: =D21+G21 -> 0 | K21: =H21+E21 -> 3 | L21: =COUNTIFS('2a. Administration'!$I:$I,Summary!$A21,'2a. Administration'!$J:$J,Summary!L$19,'2a. Administration'!$E:$E,Summary!$C$1) -> 50 | M21: =COUNTIFS('2a. Administration'!$I:$I,Summary!$A21,'2a. Administration'!$J:$J,Summary!M$19,'2a. Administration'!$E:$E,Summary!$C$1) -> 0 | N21: =COUNTIFS('2a. Administration'!$I:$I,Summary!$A21,'2a. Administration'!$J:$J,Summary!N$19,'2a. Administration'!$E:$E,Summary!$C$1) -> 0 | O21: =COUNTIFS('2a. Administration'!$I:$I,Summary!$A21,'2a. Administration'!$J:$J,Summary!O$19,'2a. Administration'!$E:$E,Summary!$D$1) -> 7 | P21: =COUNTIFS('2a. Administration'!$I:$I,Summary!$A21,'2a. Administration'!$J:$J,Summary!P$19,'2a. Administration'!$E:$E,Summary!$D$1) -> 0 | Q21: =COUNTIFS('2a. Administration'!$I:$I,Summary!$A21,'2a. Administration'!$J:$J,Summary!Q$19,'2a. Administration'!$E:$E,Summary!$D$1) -> 0 | R21: =L21+O21 -> 57 | S21: =M21+P21 -> 0 | T21: =Q21+N21 -> 0 | U21: =R21-I21 -> -27 | V21: =S21-J21 -> 0 | W21: =T21-K21 -> -3
A22: 2b | B22: Planning | C22: =COUNTIFS('2b. Planning'!$I:$I,Summary!$A22,'2b. Planning'!$C:$C,Summary!C$19,'2b. Planning'!$E:$E,Summary!$C$1) -> 155 | D22: =COUNTIFS('2b. Planning'!$I:$I,Summary!$A22,'2b. Planning'!$C:$C,Summary!D$19,'2b. Planning'!$E:$E,Summary!$C$1) -> 0 | E22: =COUNTIFS('2b. Planning'!$I:$I,Summary!$A22,'2b. Planning'!$C:$C,Summary!E$19,'2b. Planning'!$E:$E,Summary!$C$1) -> 0 | F22: =COUNTIFS('2b. Planning'!$I:$I,Summary!$A22,'2b. Planning'!$C:$C,Summary!F$19,'2b. Planning'!$E:$E,Summary!$D$1) -> 49 | G22: =COUNTIFS('2b. Planning'!$I:$I,Summary!$A22,'2b. Planning'!$C:$C,Summary!G$19,'2b. Planning'!$E:$E,Summary!$D$1) -> 2 | H22: =COUNTIFS('2b. Planning'!$I:$I,Summary!$A22,'2b. Planning'!$C:$C,Summary!H$19,'2b. Planning'!$E:$E,Summary!$D$1) -> 46 | I22: =C22+F22 -> 204 | J22: =D22+G22 -> 2 | K22: =H22+E22 -> 46 | L22: =COUNTIFS('2b. Planning'!$I:$I,Summary!$A22,'2b. Planning'!$J:$J,Summary!L$19,'2b. Planning'!$E:$E,Summary!$C$1) -> 122 | M22: =COUNTIFS('2b. Planning'!$I:$I,Summary!$A22,'2b. Planning'!$J:$J,Summary!M$19,'2b. Planning'!$E:$E,Summary!$C$1) -> 0 | N22: =COUNTIFS('2b. Planning'!$I:$I,Summary!$A22,'2b. Planning'!$J:$J,Summary!N$19,'2b. Planning'!$E:$E,Summary!$C$1) -> 0 | O22: =COUNTIFS('2b. Planning'!$I:$I,Summary!$A22,'2b. Planning'!$J:$J,Summary!O$19,'2b. Planning'!$E:$E,Summary!$D$1) -> 39 | P22: =COUNTIFS('2b. Planning'!$I:$I,Summary!$A22,'2b. Planning'!$J:$J,Summary!P$19,'2b. Planning'!$E:$E,Summary!$D$1) -> 0 | Q22: =COUNTIFS('2b. Planning'!$I:$I,Summary!$A22,'2b. Planning'!$J:$J,Summary!Q$19,'2b. Planning'!$E:$E,Summary!$D$1) -> 0 | R22: =L22+O22 -> 161 | S22: =M22+P22 -> 0 | T22: =Q22+N22 -> 0 | U22: =R22-I22 -> -43 | V22: =S22-J22 -> -2 | W22: =T22-K22 -> -46
A23: 2c | B23: Delivery | C23: =COUNTIFS('2c. Delivery'!$I:$I,Summary!$A23,'2c. Delivery'!$C:$C,Summary!C$19,'2c. Delivery'!$E:$E,Summary!$C$1) -> 27 | D23: =COUNTIFS('2c. Delivery'!$I:$I,Summary!$A23,'2c. Delivery'!$C:$C,Summary!D$19,'2c. Delivery'!$E:$E,Summary!$C$1) -> 0 | E23: =COUNTIFS('2c. Delivery'!$I:$I,Summary!$A23,'2c. Delivery'!$C:$C,Summary!E$19,'2c. Delivery'!$E:$E,Summary!$C$1) -> 0 | F23: =COUNTIFS('2c. Delivery'!$I:$I,Summary!$A23,'2c. Delivery'!$C:$C,Summary!F$19,'2c. Delivery'!$E:$E,Summary!$D$1) -> 56 | G23: =COUNTIFS('2c. Delivery'!$I:$I,Summary!$A23,'2c. Delivery'!$C:$C,Summary!G$19,'2c. Delivery'!$E:$E,Summary!$D$1) -> 2 | H23: =COUNTIFS('2c. Delivery'!$I:$I,Summary!$A23,'2c. Delivery'!$C:$C,Summary!H$19,'2c. Delivery'!$E:$E,Summary!$D$1) -> 16 | I23: =C23+F23 -> 83 | J23: =D23+G23 -> 2 | K23: =H23+E23 -> 16 | L23: =COUNTIFS('2c. Delivery'!$I:$I,Summary!$A23,'2c. Delivery'!$J:$J,Summary!L$19,'2c. Delivery'!$E:$E,Summary!$C$1) -> 20 | M23: =COUNTIFS('2c. Delivery'!$I:$I,Summary!$A23,'2c. Delivery'!$J:$J,Summary!M$19,'2c. Delivery'!$E:$E,Summary!$C$1) -> 0 | N23: =COUNTIFS('2c. Delivery'!$I:$I,Summary!$A23,'2c. Delivery'!$J:$J,Summary!N$19,'2c. Delivery'!$E:$E,Summary!$C$1) -> 1 | O23: =COUNTIFS('2c. Delivery'!$I:$I,Summary!$A23,'2c. Delivery'!$J:$J,Summary!O$19,'2c. Delivery'!$E:$E,Summary!$D$1) -> 34 | P23: =COUNTIFS('2c. Delivery'!$I:$I,Summary!$A23,'2c. Delivery'!$J:$J,Summary!P$19,'2c. Delivery'!$E:$E,Summary!$D$1) -> 0 | Q23: =COUNTIFS('2c. Delivery'!$I:$I,Summary!$A23,'2c. Delivery'!$J:$J,Summary!Q$19,'2c. Delivery'!$E:$E,Summary!$D$1) -> 3 | R23: =L23+O23 -> 54 | S23: =M23+P23 -> 0 | T23: =Q23+N23 -> 4 | U23: =R23-I23 -> -29 | V23: =S23-J23 -> -2 | W23: =T23-K23 -> -12
A24: 2d | B24: Reconciliation | C24: =COUNTIFS('2d. Reconciliation'!$I:$I,Summary!$A24,'2d. Reconciliation'!$C:$C,Summary!C$19,'2d. Reconciliation'!$E:$E,Summary!$C$1) -> 17 | D24: =COUNTIFS('2d. Reconciliation'!$I:$I,Summary!$A24,'2d. Reconciliation'!$C:$C,Summary!D$19,'2d. Reconciliation'!$E:$E,Summary!$C$1) -> 0 | E24: =COUNTIFS('2d. Reconciliation'!$I:$I,Summary!$A24,'2d. Reconciliation'!$C:$C,Summary!E$19,'2d. Reconciliation'!$E:$E,Summary!$C$1) -> 0 | F24: =COUNTIFS('2d. Reconciliation'!$I:$I,Summary!$A24,'2d. Reconciliation'!$C:$C,Summary!F$19,'2d. Reconciliation'!$E:$E,Summary!$D$1) -> 9 | G24: =COUNTIFS('2d. Reconciliation'!$I:$I,Summary!$A24,'2d. Reconciliation'!$C:$C,Summary!G$19,'2d. Reconciliation'!$E:$E,Summary!$D$1) -> 0 | H24: =COUNTIFS('2d. Reconciliation'!$I:$I,Summary!$A24,'2d. Reconciliation'!$C:$C,Summary!H$19,'2d. Reconciliation'!$E:$E,Summary!$D$1) -> 4 | I24: =C24+F24 -> 26 | J24: =D24+G24 -> 0 | K24: =H24+E24 -> 4 | L24: =COUNTIFS('2d. Reconciliation'!$I:$I,Summary!$A24,'2d. Reconciliation'!$J:$J,Summary!L$19,'2d. Reconciliation'!$E:$E,Summary!$C$1) -> 12 | M24: =COUNTIFS('2d. Reconciliation'!$I:$I,Summary!$A24,'2d. Reconciliation'!$J:$J,Summary!M$19,'2d. Reconciliation'!$E:$E,Summary!$C$1) -> 0 | N24: =COUNTIFS('2d. Reconciliation'!$I:$I,Summary!$A24,'2d. Reconciliation'!$J:$J,Summary!N$19,'2d. Reconciliation'!$E:$E,Summary!$C$1) -> 0 | O24: =COUNTIFS('2d. Reconciliation'!$I:$I,Summary!$A24,'2d. Reconciliation'!$J:$J,Summary!O$19,'2d. Reconciliation'!$E:$E,Summary!$D$1) -> 7 | P24: =COUNTIFS('2d. Reconciliation'!$I:$I,Summary!$A24,'2d. Reconciliation'!$J:$J,Summary!P$19,'2d. Reconciliation'!$E:$E,Summary!$D$1) -> 0 | Q24: =COUNTIFS('2d. Reconciliation'!$I:$I,Summary!$A24,'2d. Reconciliation'!$J:$J,Summary!Q$19,'2d. Reconciliation'!$E:$E,Summary!$D$1) -> 0 | R24: =L24+O24 -> 19 | S24: =M24+P24 -> 0 | T24: =Q24+N24 -> 0 | U24: =R24-I24 -> -7 | V24: =S24-J24 -> 0 | W24: =T24-K24 -> -4
A25: 2e | B25: Reporting | C25: =COUNTIFS('2e. Reporting'!$I:$I,Summary!$A25,'2e. Reporting'!$C:$C,Summary!C$19,'2e. Reporting'!$E:$E,Summary!$C$1) -> 49 | D25: =COUNTIFS('2e. Reporting'!$I:$I,Summary!$A25,'2e. Reporting'!$C:$C,Summary!D$19,'2e. Reporting'!$E:$E,Summary!$C$1) -> 0 | E25: =COUNTIFS('2e. Reporting'!$I:$I,Summary!$A25,'2e. Reporting'!$C:$C,Summary!E$19,'2e. Reporting'!$E:$E,Summary!$C$1) -> 0 | F25: =COUNTIFS('2e. Reporting'!$I:$I,Summary!$A25,'2e. Reporting'!$C:$C,Summary!F$19,'2e. Reporting'!$E:$E,Summary!$D$1) -> 17 | G25: =COUNTIFS('2e. Reporting'!$I:$I,Summary!$A25,'2e. Reporting'!$C:$C,Summary!G$19,'2e. Reporting'!$E:$E,Summary!$D$1) -> 0 | H25: =COUNTIFS('2e. Reporting'!$I:$I,Summary!$A25,'2e. Reporting'!$C:$C,Summary!H$19,'2e. Reporting'!$E:$E,Summary!$D$1) -> 8 | I25: =C25+F25 -> 66 | J25: =D25+G25 -> 0 | K25: =H25+E25 -> 8 | L25: =COUNTIFS('2e. Reporting'!$I:$I,Summary!$A25,'2e. Reporting'!$J:$J,Summary!L$19,'2e. Reporting'!$E:$E,Summary!$C$1) -> 49 | M25: =COUNTIFS('2e. Reporting'!$I:$I,Summary!$A25,'2e. Reporting'!$J:$J,Summary!M$19,'2e. Reporting'!$E:$E,Summary!$C$1) -> 0 | N25: =COUNTIFS('2e. Reporting'!$I:$I,Summary!$A25,'2e. Reporting'!$J:$J,Summary!N$19,'2e. Reporting'!$E:$E,Summary!$C$1) -> 0 | O25: =COUNTIFS('2e. Reporting'!$I:$I,Summary!$A25,'2e. Reporting'!$J:$J,Summary!O$19,'2e. Reporting'!$E:$E,Summary!$D$1) -> 19 | P25: =COUNTIFS('2e. Reporting'!$I:$I,Summary!$A25,'2e. Reporting'!$J:$J,Summary!P$19,'2e. Reporting'!$E:$E,Summary!$D$1) -> 0 | Q25: =COUNTIFS('2e. Reporting'!$I:$I,Summary!$A25,'2e. Reporting'!$J:$J,Summary!Q$19,'2e. Reporting'!$E:$E,Summary!$D$1) -> 0 | R25: =L25+O25 -> 68 | S25: =M25+P25 -> 0 | T25: =Q25+N25 -> 0 | U25: =R25-I25 -> 2 | V25: =S25-J25 -> 0 | W25: =T25-K25 -> -8
A27: 3a | B27: Security | C27: =COUNTIFS('3a. Security'!$I:$I,Summary!$A27,'3a. Security'!$C:$C,Summary!C$19,'3a. Security'!$E:$E,Summary!$C$1) -> 6 | D27: =COUNTIFS('3a. Security'!$I:$I,Summary!$A27,'3a. Security'!$C:$C,Summary!D$19,'3a. Security'!$E:$E,Summary!$C$1) -> 0 | E27: =COUNTIFS('3a. Security'!$I:$I,Summary!$A27,'3a. Security'!$C:$C,Summary!E$19,'3a. Security'!$E:$E,Summary!$C$1) -> 0 | F27: =COUNTIFS('3a. Security'!$I:$I,Summary!$A27,'3a. Security'!$C:$C,Summary!F$19,'3a. Security'!$E:$E,Summary!$D$1) -> 0 | G27: =COUNTIFS('3a. Security'!$I:$I,Summary!$A27,'3a. Security'!$C:$C,Summary!G$19,'3a. Security'!$E:$E,Summary!$D$1) -> 0 | H27: =COUNTIFS('3a. Security'!$I:$I,Summary!$A27,'3a. Security'!$C:$C,Summary!H$19,'3a. Security'!$E:$E,Summary!$D$1) -> 0 | I27: =C27+F27 -> 6 | J27: =D27+G27 -> 0 | K27: =H27+E27 -> 0 | L27: =COUNTIFS('3a. Security'!$I:$I,Summary!$A27,'3a. Security'!$J:$J,Summary!L$19,'3a. Security'!$E:$E,Summary!$C$1) -> 6 | M27: =COUNTIFS('3a. Security'!$I:$I,Summary!$A27,'3a. Security'!$J:$J,Summary!M$19,'3a. Security'!$E:$E,Summary!$C$1) -> 0 | N27: =COUNTIFS('3a. Security'!$I:$I,Summary!$A27,'3a. Security'!$J:$J,Summary!N$19,'3a. Security'!$E:$E,Summary!$C$1) -> 0 | O27: =COUNTIFS('3a. Security'!$I:$I,Summary!$A27,'3a. Security'!$J:$J,Summary!O$19,'3a. Security'!$E:$E,Summary!$D$1) -> 0 | P27: =COUNTIFS('3a. Security'!$I:$I,Summary!$A27,'3a. Security'!$J:$J,Summary!P$19,'3a. Security'!$E:$E,Summary!$D$1) -> 0 | Q27: =COUNTIFS('3a. Security'!$I:$I,Summary!$A27,'3a. Security'!$J:$J,Summary!Q$19,'3a. Security'!$E:$E,Summary!$D$1) -> 0 | R27: =L27+O27 -> 6 | S27: =M27+P27 -> 0 | T27: =Q27+N27 -> 0 | U27: =R27-I27 -> 0 | V27: =S27-J27 -> 0 | W27: =T27-K27 -> 0
A28: 3b | B28: User Interface & User Exp | C28: =COUNTIFS('3b. User Interface and User Exp'!$I:$I,Summary!$A28,'3b. User Interface and User Exp'!$C:$C,Summary!C$19,'3b. User Interface and User Exp'!$E:$E,Summary!$C$1) -> 2 | D28: =COUNTIFS('3b. User Interface and User Exp'!$I:$I,Summary!$A28,'3b. User Interface and User Exp'!$C:$C,Summary!D$19,'3b. User Interface and User Exp'!$E:$E,Summary!$C$1) -> 0 | E28: =COUNTIFS('3b. User Interface and User Exp'!$I:$I,Summary!$A28,'3b. User Interface and User Exp'!$C:$C,Summary!E$19,'3b. User Interface and User Exp'!$E:$E,Summary!$C$1) -> 0 | F28: =COUNTIFS('3b. User Interface and User Exp'!$I:$I,Summary!$A28,'3b. User Interface and User Exp'!$C:$C,Summary!F$19,'3b. User Interface and User Exp'!$E:$E,Summary!$D$1) -> 5 | G28: =COUNTIFS('3b. User Interface and User Exp'!$I:$I,Summary!$A28,'3b. User Interface and User Exp'!$C:$C,Summary!G$19,'3b. User Interface and User Exp'!$E:$E,Summary!$D$1) -> 0 | H28: =COUNTIFS('3b. User Interface and User Exp'!$I:$I,Summary!$A28,'3b. User Interface and User Exp'!$C:$C,Summary!H$19,'3b. User Interface and User Exp'!$E:$E,Summary!$D$1) -> 0 | I28: =C28+F28 -> 7 | J28: =D28+G28 -> 0 | K28: =H28+E28 -> 0 | L28: =COUNTIFS('3b. User Interface and User Exp'!$I:$I,Summary!$A28,'3b. User Interface and User Exp'!$J:$J,Summary!L$19,'3b. User Interface and User Exp'!$E:$E,Summary!$C$1) -> 2 | M28: =COUNTIFS('3b. User Interface and User Exp'!$I:$I,Summary!$A28,'3b. User Interface and User Exp'!$J:$J,Summary!M$19,'3b. User Interface and User Exp'!$E:$E,Summary!$C$1) -> 0 | N28: =COUNTIFS('3b. User Interface and User Exp'!$I:$I,Summary!$A28,'3b. User Interface and User Exp'!$J:$J,Summary!N$19,'3b. User Interface and User Exp'!$E:$E,Summary!$C$1) -> 0 | O28: =COUNTIFS('3b. User Interface and User Exp'!$I:$I,Summary!$A28,'3b. User Interface and User Exp'!$J:$J,Summary!O$19,'3b. User Interface and User Exp'!$E:$E,Summary!$D$1) -> 5 | P28: =COUNTIFS('3b. User Interface and User Exp'!$I:$I,Summary!$A28,'3b. User Interface and User Exp'!$J:$J,Summary!P$19,'3b. User Interface and User Exp'!$E:$E,Summary!$D$1) -> 0 | Q28: =COUNTIFS('3b. User Interface and User Exp'!$I:$I,Summary!$A28,'3b. User Interface and User Exp'!$J:$J,Summary!Q$19,'3b. User Interface and User Exp'!$E:$E,Summary!$D$1) -> 0 | R28: =L28+O28 -> 7 | S28: =M28+P28 -> 0 | T28: =Q28+N28 -> 0 | U28: =R28-I28 -> 0 | V28: =S28-J28 -> 0 | W28: =T28-K28 -> 0
A29: 3c | B29: Performance & Scalability | C29: =COUNTIFS('3c. Performance-Scalability'!$I:$I,Summary!$A29,'3c. Performance-Scalability'!$C:$C,Summary!C$19,'3c. Performance-Scalability'!$E:$E,Summary!$C$1) -> 0 | D29: =COUNTIFS('3c. Performance-Scalability'!$I:$I,Summary!$A29,'3c. Performance-Scalability'!$C:$C,Summary!D$19,'3c. Performance-Scalability'!$E:$E,Summary!$C$1) -> 0 | E29: =COUNTIFS('3c. Performance-Scalability'!$I:$I,Summary!$A29,'3c. Performance-Scalability'!$C:$C,Summary!E$19,'3c. Performance-Scalability'!$E:$E,Summary!$C$1) -> 0 | F29: =COUNTIFS('3c. Performance-Scalability'!$I:$I,Summary!$A29,'3c. Performance-Scalability'!$C:$C,Summary!F$19,'3c. Performance-Scalability'!$E:$E,Summary!$D$1) -> 6 | G29: =COUNTIFS('3c. Performance-Scalability'!$I:$I,Summary!$A29,'3c. Performance-Scalability'!$C:$C,Summary!G$19,'3c. Performance-Scalability'!$E:$E,Summary!$D$1) -> 0 | H29: =COUNTIFS('3c. Performance-Scalability'!$I:$I,Summary!$A29,'3c. Performance-Scalability'!$C:$C,Summary!H$19,'3c. Performance-Scalability'!$E:$E,Summary!$D$1) -> 0 | I29: =C29+F29 -> 6 | J29: =D29+G29 -> 0 | K29: =H29+E29 -> 0 | L29: =COUNTIFS('3c. Performance-Scalability'!$I:$I,Summary!$A29,'3c. Performance-Scalability'!$J:$J,Summary!L$19,'3c. Performance-Scalability'!$E:$E,Summary!$C$1) -> 0 | M29: =COUNTIFS('3c. Performance-Scalability'!$I:$I,Summary!$A29,'3c. Performance-Scalability'!$J:$J,Summary!M$19,'3c. Performance-Scalability'!$E:$E,Summary!$C$1) -> 0 | N29: =COUNTIFS('3c. Performance-Scalability'!$I:$I,Summary!$A29,'3c. Performance-Scalability'!$J:$J,Summary!N$19,'3c. Performance-Scalability'!$E:$E,Summary!$C$1) -> 0 | O29: =COUNTIFS('3c. Performance-Scalability'!$I:$I,Summary!$A29,'3c. Performance-Scalability'!$J:$J,Summary!O$19,'3c. Performance-Scalability'!$E:$E,Summary!$D$1) -> 6 | P29: =COUNTIFS('3c. Performance-Scalability'!$I:$I,Summary!$A29,'3c. Performance-Scalability'!$J:$J,Summary!P$19,'3c. Performance-Scalability'!$E:$E,Summary!$D$1) -> 0 | Q29: =COUNTIFS('3c. Performance-Scalability'!$I:$I,Summary!$A29,'3c. Performance-Scalability'!$J:$J,Summary!Q$19,'3c. Performance-Scalability'!$E:$E,Summary!$D$1) -> 0 | R29: =L29+O29 -> 6 | S29: =M29+P29 -> 0 | T29: =Q29+N29 -> 0 | U29: =R29-I29 -> 0 | V29: =S29-J29 -> 0 | W29: =T29-K29 -> 0
A30: 3d | B30: Support-Maintenance | C30: =COUNTIFS('3d. Support-Maintenance'!$I:$I,Summary!$A30,'3d. Support-Maintenance'!$C:$C,Summary!C$19,'3d. Support-Maintenance'!$E:$E,Summary!$C$1) -> 5 | D30: =COUNTIFS('3d. Support-Maintenance'!$I:$I,Summary!$A30,'3d. Support-Maintenance'!$C:$C,Summary!D$19,'3d. Support-Maintenance'!$E:$E,Summary!$C$1) -> 0 | E30: =COUNTIFS('3d. Support-Maintenance'!$I:$I,Summary!$A30,'3d. Support-Maintenance'!$C:$C,Summary!E$19,'3d. Support-Maintenance'!$E:$E,Summary!$C$1) -> 0 | F30: =COUNTIFS('3d. Support-Maintenance'!$I:$I,Summary!$A30,'3d. Support-Maintenance'!$C:$C,Summary!F$19,'3d. Support-Maintenance'!$E:$E,Summary!$D$1) -> 2 | G30: =COUNTIFS('3d. Support-Maintenance'!$I:$I,Summary!$A30,'3d. Support-Maintenance'!$C:$C,Summary!G$19,'3d. Support-Maintenance'!$E:$E,Summary!$D$1) -> 0 | H30: =COUNTIFS('3d. Support-Maintenance'!$I:$I,Summary!$A30,'3d. Support-Maintenance'!$C:$C,Summary!H$19,'3d. Support-Maintenance'!$E:$E,Summary!$D$1) -> 0 | I30: =C30+F30 -> 7 | J30: =D30+G30 -> 0 | K30: =H30+E30 -> 0 | L30: =COUNTIFS('3d. Support-Maintenance'!$I:$I,Summary!$A30,'3d. Support-Maintenance'!$J:$J,Summary!L$19,'3d. Support-Maintenance'!$E:$E,Summary!$C$1) -> 5 | M30: =COUNTIFS('3d. Support-Maintenance'!$I:$I,Summary!$A30,'3d. Support-Maintenance'!$J:$J,Summary!M$19,'3d. Support-Maintenance'!$E:$E,Summary!$C$1) -> 0 | N30: =COUNTIFS('3d. Support-Maintenance'!$I:$I,Summary!$A30,'3d. Support-Maintenance'!$J:$J,Summary!N$19,'3d. Support-Maintenance'!$E:$E,Summary!$C$1) -> 0 | O30: =COUNTIFS('3d. Support-Maintenance'!$I:$I,Summary!$A30,'3d. Support-Maintenance'!$J:$J,Summary!O$19,'3d. Support-Maintenance'!$E:$E,Summary!$D$1) -> 2 | P30: =COUNTIFS('3d. Support-Maintenance'!$I:$I,Summary!$A30,'3d. Support-Maintenance'!$J:$J,Summary!P$19,'3d. Support-Maintenance'!$E:$E,Summary!$D$1) -> 0 | Q30: =COUNTIFS('3d. Support-Maintenance'!$I:$I,Summary!$A30,'3d. Support-Maintenance'!$J:$J,Summary!Q$19,'3d. Support-Maintenance'!$E:$E,Summary!$D$1) -> 0 | R30: =L30+O30 -> 7 | S30: =M30+P30 -> 0 | T30: =Q30+N30 -> 0 | U30: =R30-I30 -> 0 | V30: =S30-J30 -> 0 | W30: =T30-K30 -> 0
A31: 3e | B31: Reliability-Availability | C31: =COUNTIFS('3e. Reliability-Availability'!$I:$I,Summary!$A31,'3e. Reliability-Availability'!$C:$C,Summary!C$19,'3e. Reliability-Availability'!$E:$E,Summary!$C$1) -> 4 | D31: =COUNTIFS('3e. Reliability-Availability'!$I:$I,Summary!$A31,'3e. Reliability-Availability'!$C:$C,Summary!D$19,'3e. Reliability-Availability'!$E:$E,Summary!$C$1) -> 0 | E31: =COUNTIFS('3e. Reliability-Availability'!$I:$I,Summary!$A31,'3e. Reliability-Availability'!$C:$C,Summary!E$19,'3e. Reliability-Availability'!$E:$E,Summary!$C$1) -> 0 | F31: =COUNTIFS('3e. Reliability-Availability'!$I:$I,Summary!$A31,'3e. Reliability-Availability'!$C:$C,Summary!F$19,'3e. Reliability-Availability'!$E:$E,Summary!$D$1) -> 4 | G31: =COUNTIFS('3e. Reliability-Availability'!$I:$I,Summary!$A31,'3e. Reliability-Availability'!$C:$C,Summary!G$19,'3e. Reliability-Availability'!$E:$E,Summary!$D$1) -> 0 | H31: =COUNTIFS('3e. Reliability-Availability'!$I:$I,Summary!$A31,'3e. Reliability-Availability'!$C:$C,Summary!H$19,'3e. Reliability-Availability'!$E:$E,Summary!$D$1) -> 0 | I31: =C31+F31 -> 8 | J31: =D31+G31 -> 0 | K31: =H31+E31 -> 0 | L31: =COUNTIFS('3e. Reliability-Availability'!$I:$I,Summary!$A31,'3e. Reliability-Availability'!$J:$J,Summary!L$19,'3e. Reliability-Availability'!$E:$E,Summary!$C$1) -> 4 | M31: =COUNTIFS('3e. Reliability-Availability'!$I:$I,Summary!$A31,'3e. Reliability-Availability'!$J:$J,Summary!M$19,'3e. Reliability-Availability'!$E:$E,Summary!$C$1) -> 0 | N31: =COUNTIFS('3e. Reliability-Availability'!$I:$I,Summary!$A31,'3e. Reliability-Availability'!$J:$J,Summary!N$19,'3e. Reliability-Availability'!$E:$E,Summary!$C$1) -> 0 | O31: =COUNTIFS('3e. Reliability-Availability'!$I:$I,Summary!$A31,'3e. Reliability-Availability'!$J:$J,Summary!O$19,'3e. Reliability-Availability'!$E:$E,Summary!$D$1) -> 4 | P31: =COUNTIFS('3e. Reliability-Availability'!$I:$I,Summary!$A31,'3e. Reliability-Availability'!$J:$J,Summary!P$19,'3e. Reliability-Availability'!$E:$E,Summary!$D$1) -> 0 | Q31: =COUNTIFS('3e. Reliability-Availability'!$I:$I,Summary!$A31,'3e. Reliability-Availability'!$J:$J,Summary!Q$19,'3e. Reliability-Availability'!$E:$E,Summary!$D$1) -> 0 | R31: =L31+O31 -> 8 | S31: =M31+P31 -> 0 | T31: =Q31+N31 -> 0 | U31: =R31-I31 -> 0 | V31: =S31-J31 -> 0 | W31: =T31-K31 -> 0
A32: 3f | B32: Integration | C32: =COUNTIFS('3f. Integration'!$I:$I,Summary!$A32,'3f. Integration'!$C:$C,Summary!C$19,'3f. Integration'!$E:$E,Summary!$C$1) -> 12 | D32: =COUNTIFS('3f. Integration'!$I:$I,Summary!$A32,'3f. Integration'!$C:$C,Summary!D$19,'3f. Integration'!$E:$E,Summary!$C$1) -> 0 | E32: =COUNTIFS('3f. Integration'!$I:$I,Summary!$A32,'3f. Integration'!$C:$C,Summary!E$19,'3f. Integration'!$E:$E,Summary!$C$1) -> 0 | F32: =COUNTIFS('3f. Integration'!$I:$I,Summary!$A32,'3f. Integration'!$C:$C,Summary!F$19,'3f. Integration'!$E:$E,Summary!$D$1) -> 4 | G32: =COUNTIFS('3f. Integration'!$I:$I,Summary!$A32,'3f. Integration'!$C:$C,Summary!G$19,'3f. Integration'!$E:$E,Summary!$D$1) -> 0 | H32: =COUNTIFS('3f. Integration'!$I:$I,Summary!$A32,'3f. Integration'!$C:$C,Summary!H$19,'3f. Integration'!$E:$E,Summary!$D$1) -> 1 | I32: =C32+F32 -> 16 | J32: =D32+G32 -> 0 | K32: =H32+E32 -> 1 | L32: =COUNTIFS('3f. Integration'!$I:$I,Summary!$A32,'3f. Integration'!$J:$J,Summary!L$19,'3f. Integration'!$E:$E,Summary!$C$1) -> 12 | M32: =COUNTIFS('3f. Integration'!$I:$I,Summary!$A32,'3f. Integration'!$J:$J,Summary!M$19,'3f. Integration'!$E:$E,Summary!$C$1) -> 0 | N32: =COUNTIFS('3f. Integration'!$I:$I,Summary!$A32,'3f. Integration'!$J:$J,Summary!N$19,'3f. Integration'!$E:$E,Summary!$C$1) -> 0 | O32: =COUNTIFS('3f. Integration'!$I:$I,Summary!$A32,'3f. Integration'!$J:$J,Summary!O$19,'3f. Integration'!$E:$E,Summary!$D$1) -> 4 | P32: =COUNTIFS('3f. Integration'!$I:$I,Summary!$A32,'3f. Integration'!$J:$J,Summary!P$19,'3f. Integration'!$E:$E,Summary!$D$1) -> 0 | Q32: =COUNTIFS('3f. Integration'!$I:$I,Summary!$A32,'3f. Integration'!$J:$J,Summary!Q$19,'3f. Integration'!$E:$E,Summary!$D$1) -> 0 | R32: =L32+O32 -> 16 | S32: =M32+P32 -> 0 | T32: =Q32+N32 -> 0 | U32: =R32-I32 -> 0 | V32: =S32-J32 -> 0 | W32: =T32-K32 -> -1
A33: 3g | B33: Configurability | C33: =COUNTIFS('3g. Configurability'!$I:$I,Summary!$A33,'3g. Configurability'!$C:$C,Summary!C$19,'3g. Configurability'!$E:$E,Summary!$C$1) -> 3 | D33: =COUNTIFS('3g. Configurability'!$I:$I,Summary!$A33,'3g. Configurability'!$C:$C,Summary!D$19,'3g. Configurability'!$E:$E,Summary!$C$1) -> 0 | E33: =COUNTIFS('3g. Configurability'!$I:$I,Summary!$A33,'3g. Configurability'!$C:$C,Summary!E$19,'3g. Configurability'!$E:$E,Summary!$C$1) -> 0 | F33: =COUNTIFS('3g. Configurability'!$I:$I,Summary!$A33,'3g. Configurability'!$C:$C,Summary!F$19,'3g. Configurability'!$E:$E,Summary!$D$1) -> 1 | G33: =COUNTIFS('3g. Configurability'!$I:$I,Summary!$A33,'3g. Configurability'!$C:$C,Summary!G$19,'3g. Configurability'!$E:$E,Summary!$D$1) -> 0 | H33: =COUNTIFS('3g. Configurability'!$I:$I,Summary!$A33,'3g. Configurability'!$C:$C,Summary!H$19,'3g. Configurability'!$E:$E,Summary!$D$1) -> 0 | I33: =C33+F33 -> 4 | J33: =D33+G33 -> 0 | K33: =H33+E33 -> 0 | L33: =COUNTIFS('3g. Configurability'!$I:$I,Summary!$A33,'3g. Configurability'!$J:$J,Summary!L$19,'3g. Configurability'!$E:$E,Summary!$C$1) -> 3 | M33: =COUNTIFS('3g. Configurability'!$I:$I,Summary!$A33,'3g. Configurability'!$J:$J,Summary!M$19,'3g. Configurability'!$E:$E,Summary!$C$1) -> 0 | N33: =COUNTIFS('3g. Configurability'!$I:$I,Summary!$A33,'3g. Configurability'!$J:$J,Summary!N$19,'3g. Configurability'!$E:$E,Summary!$C$1) -> 0 | O33: =COUNTIFS('3g. Configurability'!$I:$I,Summary!$A33,'3g. Configurability'!$J:$J,Summary!O$19,'3g. Configurability'!$E:$E,Summary!$D$1) -> 1 | P33: =COUNTIFS('3g. Configurability'!$I:$I,Summary!$A33,'3g. Configurability'!$J:$J,Summary!P$19,'3g. Configurability'!$E:$E,Summary!$D$1) -> 0 | Q33: =COUNTIFS('3g. Configurability'!$I:$I,Summary!$A33,'3g. Configurability'!$J:$J,Summary!Q$19,'3g. Configurability'!$E:$E,Summary!$D$1) -> 0 | R33: =L33+O33 -> 4 | S33: =M33+P33 -> 0 | T33: =Q33+N33 -> 0 | U33: =R33-I33 -> 0 | V33: =S33-J33 -> 0 | W33: =T33-K33 -> 0
A34: 3h | B34: Compliance | C34: =COUNTIFS('3h. Compliance'!$I:$I,Summary!$A34,'3h. Compliance'!$C:$C,Summary!C$19,'3h. Compliance'!$E:$E,Summary!$C$1) -> 4 | D34: =COUNTIFS('3h. Compliance'!$I:$I,Summary!$A34,'3h. Compliance'!$C:$C,Summary!D$19,'3h. Compliance'!$E:$E,Summary!$C$1) -> 0 | E34: =COUNTIFS('3h. Compliance'!$I:$I,Summary!$A34,'3h. Compliance'!$C:$C,Summary!E$19,'3h. Compliance'!$E:$E,Summary!$C$1) -> 0 | F34: =COUNTIFS('3h. Compliance'!$I:$I,Summary!$A34,'3h. Compliance'!$C:$C,Summary!F$19,'3h. Compliance'!$E:$E,Summary!$D$1) -> 3 | G34: =COUNTIFS('3h. Compliance'!$I:$I,Summary!$A34,'3h. Compliance'!$C:$C,Summary!G$19,'3h. Compliance'!$E:$E,Summary!$D$1) -> 0 | H34: =COUNTIFS('3h. Compliance'!$I:$I,Summary!$A34,'3h. Compliance'!$C:$C,Summary!H$19,'3h. Compliance'!$E:$E,Summary!$D$1) -> 0 | I34: =C34+F34 -> 7 | J34: =D34+G34 -> 0 | K34: =H34+E34 -> 0 | L34: =COUNTIFS('3h. Compliance'!$I:$I,Summary!$A34,'3h. Compliance'!$J:$J,Summary!L$19,'3h. Compliance'!$E:$E,Summary!$C$1) -> 4 | M34: =COUNTIFS('3h. Compliance'!$I:$I,Summary!$A34,'3h. Compliance'!$J:$J,Summary!M$19,'3h. Compliance'!$E:$E,Summary!$C$1) -> 0 | N34: =COUNTIFS('3h. Compliance'!$I:$I,Summary!$A34,'3h. Compliance'!$J:$J,Summary!N$19,'3h. Compliance'!$E:$E,Summary!$C$1) -> 0 | O34: =COUNTIFS('3h. Compliance'!$I:$I,Summary!$A34,'3h. Compliance'!$J:$J,Summary!O$19,'3h. Compliance'!$E:$E,Summary!$D$1) -> 3 | P34: =COUNTIFS('3h. Compliance'!$I:$I,Summary!$A34,'3h. Compliance'!$J:$J,Summary!P$19,'3h. Compliance'!$E:$E,Summary!$D$1) -> 0 | Q34: =COUNTIFS('3h. Compliance'!$I:$I,Summary!$A34,'3h. Compliance'!$J:$J,Summary!Q$19,'3h. Compliance'!$E:$E,Summary!$D$1) -> 0 | R34: =L34+O34 -> 7 | S34: =M34+P34 -> 0 | T34: =Q34+N34 -> 0 | U34: =R34-I34 -> 0 | V34: =S34-J34 -> 0 | W34: =T34-K34 -> 0
B35: Total | C35: =SUM(C21:C25,C27:C34) -> 352 | D35: =SUM(D21:D25,D27:D34) -> 0 | E35: =SUM(E21:E25,E27:E34) -> 0 | F35: =SUM(F21:F25,F27:F34) -> 172 | G35: =SUM(G21:G25,G27:G34) -> 4 | H35: =SUM(H21:H25,H27:H34) -> 78 | I35: =SUM(I21:I25,I27:I34) -> 524 | J35: =SUM(J21:J25,J27:J34) -> 4 | ... W35: =SUM(W21:W25,W27:W34) -> -74

Sheet 2a. Administration
A1: 2a. | B1: Administration. In terms of managing business-level configurations and rules, the Software shall: | C1: Fulfil Certis' Requirements? (Yes/No/Partial) | D1: Remarks | E1: SG (X if required SX Showstopper) | F1: AU (X if required) | G1: Revised Requirements | H1: Certis Remarks | I1: Indicator | J1: Response (Yes/No/Partial) | K1: Remarks | L1: Cadence Related
A2: i. | B2: Role-Based Access Control
B3: Allow the System Administrator to define and manage user roles, each with specific permissions and access rights. Access levels should be aligned with job responsibilities to enforce the principle of least privilege. | C3: Y | E3: SX | F3: X | G3: SX | I3: 2a | J3: Y | L3: n | O3: BU Admin x 1 CLS/CAS/SLS Admin x 2 Segment Head x 5 Demand Mgr x 5 Divison Mgr x 25 OC x -- Cluster Exec x -- Site Supervisor x -- Officer x -- CICC Demand Mgr CICC Duty OM CICC Ops Planner CICC Time Admin Line HR QMT Deployment Mgr Deployment Exec
A4: ii. | B4: Data-level Access Control
B5: Allow the system administrator to assign granular permissions, with users having access (i.e. a combination of CRUD rights) to only specific records/groups of records within the Software Eg, two users having access to same screen might have a different level of Authorization based on role, data and action to perform on the screen | C5: Y | E5: SX | F5: X | G5: SX | I5: 2a | J5: Y | K5: Part of custom RBAC | L5: Y
A6: iii. | B6: Segregation of Duties (SOD)
B7: 1. Include functionality to identify and report potential role conflicts within the access control structure. This helps prevent situations where a single user may have conflicting or incompatible duties. For example, employees given access rights to update rosters shall not be able to update a roster which he/she is assigned to. | C7: Y | E7: SX | F7: X | G7: SX | I7: 2a | J7: Y | K7: Part of custom RBAC | L7: Y
B8: 2. Functionality shall extend to workflows and business processes. The Software should allow administrators to define and enforce the separation of critical tasks to prevent unauthorized or conflicting actions. | C8: Y | E8: SX | F8: X | G8: SX | I8: 2a | J8: Y | K8: These would need to be specified and can be built dynamically or if more static may be directly incorporated. | L8: Y
B9: 3. Pre-built and configurable workflows to enable notification and approval processes across SOD layers, shall be included. | C9: Y | D9: Approval workflows are pre-built into the system based on hierarchy and/or direct supervisor. | E9: SX | F9: X | G9: SX | I9: 2a | J9: Y | K9: Same as above. | L9: Y
A10: iv. | B10: Access Monitoring and Logging
B11: User Activity Logging - Log user activities, including login attempts, access to sensitive data, and changes to configuration settings. Detailed logs should be maintained to track user actions for auditing and forensic purposes. | C11: Y | E11: SX | F11: X | G11: SX | I11: 2a | J11: Y | L11: n
B12: Real-time Monitoring and Alerts - Implement real-time monitoring capabilities to detect and alert administrators about suspicious or unauthorized activities. Automated alerts should be triggered based on predefined thresholds and patterns indicative of security risks. | C12: Y | E12: SX | F12: X | G12: SX | I12: 2a | J12: Y | L12: Y
B13: Audit trails - The software must provide comprehensive audit trails that capture all relevant access control activities and changes. These audit trails should be easily accessible via a self-service user interface within the Software for internal and external audits to demonstrate compliance. | C13: Y | E13: SX | F13: X | G13: SX | I13: 2a | J13: Y | L13: n
A14: v. | B14: Automatic Archival of users
B15: Have the capability to automatically archive data as “housekeeping” to maintain only active data in the system. This shall be governed by rules e.g. User has not been rostered for 30 days or User has not performed a shift in 30 days, e.g. Rosters are archived after 12months post-execution, but retained for a minimum of 7 years. | C15: Y | D15: Currently data is retained for 7 years. Rules around "housekeeping" and "rules" would necessitate extension of the existing functionality. | E15: SX | F15: X | G15: SX | I15: 2a | J15: Y | L15: n
A16: vi. | B16: Contract Creation/Import
B17: The solution must support the automated creation or import of master data from SAP S/4HANA. | C17: Y | E17: SX | F17: X | G17: SX | I17: 2a | J17: Y | L17: n
A18: vii. | B18: Types of work/demand items – include the following work/demand item types
B19: The solution must allow configurable categorisation of work or demand items to align with operational needs such as deployable, billable, and user-defined demand types Also the same information must be available in reports | C19: Y | D19: These can be labelled with tags or CG/CSG. | E19: SX | F19: X | G19: X | H19: Requires Demand Object | I19: 2a | J19: Y | L19: n
A20: viii. | B20: Employee Attributes
B21: The solution must support configurable employee attributes to enable accurate rostering, role assignment, and compliance tracking. | C21: Y | E21: SX | F21: X | G21: X | I21: 2a | J21: Y | L21: n
A22: ix. | B22: Compliance Functions
B23: The solution must support the application of relevant industrial awards, enterprise agreements, and employment policies to ensure compliance with applicable wage, hour, and employment regulations. | C23: Y | E23: SX | F23: X | G23: SX | I23: 2a | J23: Y | L23: n
A24: x. | B24: Leave and Accrual Tracking Functions
B25: The solution must provide configurable leave and accrual management capabilities that support compliance with local regulations, company policies, and relevant industrial awards. It should enable the application of varying leave rules, entitlements, and approval workflows across different employee types, business units, and operating jurisdictions | C25: Y | D25: This is handled by SAP and then the banks and values are pushed to WorkAxle. WorkAxle also has local time banks for WFM based accruals and tracking that need to be captured in addition to the standard HR banks. | E25: X | F25: X | G25: X | I25: 2a | J25: Y | K25: This is handled by SAP and then the banks and values are pushed to WorkAxle. WorkAxle also has local time banks for WFM based accruals and tracking that need to be captured in addition to the standard HR banks. | L25: n
A26: xi. | B26: Payroll Calculation Capabilities
B27: The solution must support accurate and automated interpretation of timesheet data in line with applicable industrial awards, enterprise agreements, and company policies. It must be capable of applying complex working conditions such as overtime, shift differentials, and allowances, and provide flexibility to accommodate different rules by employee type, business unit, and union agreements. The interpreted data must integrate seamlessly with SAP SuccessFactors Employee Central Payroll for processing. | C27: Y | E27: SX | F27: X | G27: SX | H27: Handled by SF | I27: 2a | J27: Y | L27: n
A28: xii. | B28: Other Payroll Calculation Capabilities
B29: The solution must support automated triggering of allowances based on configurable conditions. These triggers may be based on, but are not limited to, criteria such as site, task, position, or individual employee level. Triggers should also be configurable based on the number of days or hours worked, and after crossing specific thresholds—such as exceeding certain working hours—with the ability to define minimum and maximum allowance limits per day, week, or defined period. | C29: Y | D29: Would need complete list of detailed requirements for this but we have a detailed rule engine that can handle many complex situations and is the most flexible and modern rule engine on the market for enterprise level WFM. | E29: SX | F29: X | G29: SX | H29: Manual Tag Paycode is allowed. Pay rules to incentives & Allowances | I29: 2a | J29: Y | L29: n
A30: xiii. | B30: Basic employee award interpretation – have the capability to interpret and calculate Employee Agreement terms of: | F30: Recommend deleting and providing the copies of the relevant awards and enterprise agreements.
B31: 1) Overtime each day stands alone | C31: Y | E31: SX | G31: N | H31: Not Required | I31: 2a | L31: n
B32: 2) Automatic Meal Allowance on 2nd Allowance (EBA) after 5hrs work | C32: Y | E32: X | G32: N | H32: Not Required | I32: 2a | L32: n
B33: 3) Short Shift Allowance (EBA) | C33: Y | E33: SX | G33: N | H33: Not Required | I33: 2a | L33: n
B34: 4) Broken Shift Allowance (EBA) | C34: Y | E34: SX | G34: N | H34: Not Required | I34: 2a | L34: n
B35: 5) Day Loading (conditional on start on or before 5.30am start of on or after 18.30 finish) | C35: Y | E35: X | G35: N | H35: Not Required | I35: 2a | L35: n
B36: 6) PHNW payable on off Days for 7-day workers (EBA and award) | C36: Y | E36: X | G36: N | H36: Not Required | I36: 2a | L36: n
B37: 7) Leave Loading automatic calculation payable on either 17.5% of higher loading that would have been earned if working | C37: P | D37: Need more specific information | E37: X | G37: N | H37: Not Required | I37: 2a | L37: n
B38: 8) Ability to distinguish when Rotating or Permanent Night Loading is payable, when 2/3 of ordinary shifts start between 00:00 and 06:00 then Permanent night loading is payable. | C38: Y | E38: X | G38: N | H38: Not Required | I38: 2a | L38: n
B39: 9)Ability to seamlessly integrate payroll and relate information such as industry award and what level to pay personnel. | C39: Y | E39: SX | G39: N | H39: Not Required | I39: 2a | L39: n
B40: 10) Has the demonstrated capability to interpret all aspects of the Security Services Industry Award [MA000016] | C40: P | D40: Has demonstratably handled similar complexity awards within AU but never specifically the Security Services Industry Award. | E40: X | G40: N | H40: Not Required | I40: 2a | L40: n
B41: 11) Can update base pay rates, allowances and loadings in accordance with annual wage review cycles from S4 HANA and Successfactors without additional programming or vendor support | C41: Y | E41: SX | G41: N | H41: SF or S4 to handle Time Eval | I41: 2a | L41: n
A42: xiv. | B42: Time Tolerance/Grace Period/Rounding Rules
B43: The system must enable the configuration of time tolerance and grace period rules to support fair and compliant adjustment of attendance records. These rules should be adaptable based on operational needs, award or policy requirements, and associated with relevant roles, shifts, or demand types. | C43: Y | E43: SX | F43: X | G43: SX | I43: 2a | J43: Y | L43: n
A44: xv. | B44: Handling of Public Holidays
B45: The solution must support the configuration and application of public holiday rules to ensure accurate rostering, entitlement management, and award interpretation. It should accommodate varying public holiday arrangements based on location, business unit, site, or employee type, and allow for flexible rostering requirements during public holidays. | C45: Y | D45: Specifics of these requirements may affect this answer. | E45: SX | F45: X | G45: SX | I45: 2a | J45: Y | L45: n
A46: xvi. | B46: Special Functions for Partners/Sub-contractors ' Certis employs the services of sub-contractors who provide workforce to supplement Certis’ contract demands. The Software shall have:
B47: The solution must support the engagement and management of sub-contractor organisations that supplement Certis’ workforce. It should provide configurable access and delegation capabilities to enable sub-contractors to receive rostered work, allocate their personnel, and meet operational and compliance requirements. The system must support identity management for personnel working across multiple subcontractors, ensure application of relevant fatigue and licensing rules, facilitate compliance with client-specific authorisation requirements, and enable document exchange and verification through integration with external systems and Certis' ERP. | C47: Y | D47: Specifics of these requirements may affect this answer. Specifically the operational flow and "document exchange and verification". | E47: X | F47: X | G47: N | H47: Integrate RCMS via API | I47: 2a | L47: n
B48: Order Receiving | C48: Fulfil Certis' Requirements? (Yes/No/Partial) | D48: Remarks
A49: i | B49: The system should integrate with S4 HANA for Sales Order creation and subsequently create the work order in NGRS from S4 HANA. | C49: Y | E49: SX | G49: SX | I49: 2a | J49: Y | L49: n
A50: ii | B50: The system should receive adhoc orders from Perspective SO/IRIMS and create the corresponding work orders in NGRS. For example, SO Perspective should be able to create work orders in NGRS (if any event of back dated creation, will require for approval workflow) | C50: Y | E50: SX | G50: N | H50: Manual/ Give ISG to have ability to create urgent Demand via NGRS | I50: 2a | L50: n
A51: iii | B51: The system will be able to allow user to tag the NGRS Work Order to S4 HANA Contract | C51: Y | E51: SX | G51: N | H51: Integrate with L2W IBMS | I51: 2a | L51: n
A52: iv | B52: The system should automatically create demand with all demand details updated, including coverage, constraints, allowances, site, longitude, latitude, and address, when NGRS receives the details. | C52: Y | E52: SX | G52: SX | I52: 2a | J52: Y
B53: Onboarding | C53: Fulfil Certis' Requirements? (Yes/No/Partial) | D53: Remarks
A54: i. | B54: The system must support the onboarding process for new staff, customers, and resource contractors within the NGRS framework, S4 HANA and other Certis Systems | C54: Y | D54: Users can automatically be added, archived, deleted directly through the integration with other systems or directly in the system | E54: SX | G54: SX | H54: For resource contractors via RCMS integration FT/PT via S4 Integration | I54: 2a | J54: Y | L54: n
A55: ii | B55: The system must support the onboarding process for new billable contracts and outcome-based contracts within the NGRS and S4 HANA. | C55: Y | E55: SX | G55: N | H55: System just need to categorize Work demand. Reference 2a vii | I55: 2a | L55: n
A56: iii. | B56: The system must support the integration process for new third-party systems to and from the NGRS framework. (AEMS, EJobCard, ATONCE, TITUS, RCMS, CADENCE, MASS+, Preboard Module, Allegro, LTMS, SF, SAP WBS) | C56: Y | E56: SX | G56: SX | I56: 2a | J56: Y | L56: n
A57: iv. | B57: The system must support the configuration of the Business Organizational Structure within the NGRS framework, including the setup and management of organizational units | C57: Y | E57: SX | G57: SX | I57: 2a | J57: Y | L57: n
A58: v | B58: The system must be capable of identifying the Business Unit (BU), Segment, or Division to which Assignment A belongs by tagging the organizational unit to the respective officer | C58: Y | E58: SX | G58: N | H58: same as 2a iV | I58: 2a | L58: n
A59: vi | B59: The system must be capable of identifying the Business Unit (BU), Segment, or Division to which Officer A belongs | C59: Y | E59: SX | G59: N | H59: same as 2a iV | I59: 2a | L59: n
A60: vii | B60: The system must support the creation and onboarding of new constraints, including the specification of start and end dates, similar to the functionality provided by Certis System | C60: Y | E60: SX | G60: SX | H60: Creation of Contraints from LTMS & SF | I60: 2a | J60: Y | L60: n
A61: viii | B61: The system must support the creation and onboarding of new coverage, including the specification of start and end dates. | C61: Y | E61: SX | G61: SX | H61: Control at Super Admin Level | I61: 2a | J61: Y | L61: n
A62: ix | B62: The system must support the creation and onboarding of new shift patterns, which can be tagged to officers or demand, and must include the specification of start and end dates | C62: Y | E62: SX | G62: SX | H62: Control at Super Admin Level | I62: 2a | J62: Y | L62: n
A63: x | B63: The system must support the creation and onboarding of new allowances, including the specification of start and end dates | C63: Y | E63: SX | G63: SX | H63: Control at SF Level | I63: 2a | J63: Y | L63: n
A64: xi | B64: The system must support the creation and onboarding of new incentives, including the specification of start and end dates | C64: Y | E64: SX | G64: SX | H64: Control at SF Level | I64: 2a | J64: Y | L64: n
A65: xii | B65: The system must support the creation and onboarding of new qualifications, including the specification of start and end dates | C65: Y | E65: SX | G65: N | H65: Integrate with Learning & Training Management System (LTMS) & S4 | I65: 2a | L65: n | M65: LTMS
A66: xiii | B66: The system must support administrators in creating and onboarding new users within the NGRS framework. | C66: Y | E66: SX | G66: N | H66: Integrate with SF & S4 | I66: 2a | L66: n
A67: xiv | B67: The system must define and manage access rights and user metrics within the NGRS framework | C67: Y | E67: SX | G67: SX | H67: Control at Super Admin Level | I67: 2a | J67: Y | L67: n
A68: xv | B68: The system must support the creation and onboarding of Cost/Profit Centers within the NGRS framework | C68: Y | E68: SX | G68: N | H68: Integrate with SF & S4. Creation of CC & PC by GF | I68: 2a | L68: n
A69: xvi | B69: The system must specify whether users from Business Unit A are permitted to view details of officers and demand from Business Unit B | C69: Y | E69: SX | G69: N | H69: Control at Super Admin Level | I69: 2a | L69: n
A70: xvii | B70: The system must be capable of capturing training attendance before it is posted to the Business Unit (BU) and must have the capability to monitor and regulate overtime (OT) hours. If the system is unable to perform these functions, it must be integrated with the Certis system | C70: Y | E70: SX | G70: N | H70: Integrate with Learning & Training Management System (LTMS) & S4 Attendence in LTMS/ S4 can be read in NGRS | I70: 2a | L70: n | M70: LTMS
A71: xviii | B71: The system must support the process for setting up and creating NGRS User roles within the NGRS framework. Employee roles define by Supervisor/OM | C71: Y | E71: SX | G71: SX | I71: 2a | J71: Y | L71: n
B72: Qualification/Constraint | C72: Fulfil Certis' Requirements? (Yes/No/Partial) | D72: Remarks
A73: i. | B73: The system must support the functionality to enable the grouping of qualifications into templates. | C73: Y | E73: SX | G73: SX | I73: 2a | J73: Y | L73: n
A74: ii | B74: The system must support and provide categories in qualifications, such as gender, license, nationality, and skillset | C74: Y | E74: SX | G74: SX | I74: 2a | J74: Y | L74: n
A75: iii. | B75: The system must be capable to identify qualifications as either hard (regulation-based) or soft (client-based). | C75: Y | E75: SX | G75: SX | I75: 2a | J75: Y | L75: n
A76: iv. | B76: The system must allow users to upload qualifications or supporting documents and automatically updates the mentioned qualifications in NGRS. | C76: Y | D76: Usually this is done with checkboxes or dropdowns. for either TRUE or FALSE or multi-select. Document storage would ideally be done in SAP, and WorkAxle would have the effective date and the value of the certification. | E76: X | G76: N | H76: Integrate with LTMS & S4 Cover under Workflow Approval | I76: 2a | L76: n | M76: LTMS
A77: v | B77: The system must allow users to view and download officer qualifications from NGRS, based on ID or skill sets. | C77: Y | E77: SX | G77: N | H77: Manager App must be able to view officer Qualifications | I77: 2a | L77: n | M77: LTMS
A78: vi | B78: The system must have the functionality/ features automation of OJT attendance to qualification once approved, utilizing an in-built approval system. For new recruits, the process flows from OJT to qualification, with a push to Certis System and then to NGRS. If not updated in time, it will result in a violation | C78: Y | D78: Usually this flows from SAP directly to WorkAxle where we store the final result/qualification/affiliation. | E78: X | G78: N | I78: 2a | L78: n | M78: LTMS
A79: vii | B79: The system must have functionality to allow the overriding of constraints and include an in-built approval system with the capability to store supporting documents | C79: P | D79: Supporting documents functionality needs to be further elaborated. Overriding is always an option. | E79: X | G79: X | H79: Need Workflow approval Storing of supporting doc is optional | I79: 2a | J79: Y | L79: n
A80: viii | B80: The system must have the functionality to have an either/or function for constraints | C80: Y | E80: SX | G80: SX | I80: 2a | J80: Y | L80: n
A81: ix | B81: The system allows for a configuration table to read qualification groupings related to either/or constraints | C81: Y | E81: X | G81: X | I81: 2a | J81: Y | L81: n
A82: x | B82: The system allows for the configuration of fatigue rules for each role, such as a 14-hour fatigue rule for Scheme A | C82: Y | E82: SX | G82: SX | I82: 2a | J82: Y | L82: n
A83: xi | B83: The system should update the qualification data in real-time, ensuring that any changes made in Certis Systemare instantly synchronized with NGRS | C83: Y | E83: SX | G83: SX | I83: 2a | J83: Y | L83: n
A84: xii | B84: The system ia able to handle the constraints associated with arms-related qualifications | C84: Y | E84: SX | G84: SX | I84: 2a | J84: Y | L84: n
A85: xiii | B85: The system should enable users to upload and send multiple officers for approval within a specified period. Integrated with Certis System can manage the uploading process to NGRS | C85: Y | E85: X | G85: X | I85: 2a | J85: Y | L85: n
A86: xiv | B86: The system should allow users to set constraints for each organizational unit and enable the selection of different rule sets and approval workflows for each business unit | C86: Y | E86: X | G86: X | I86: 2a | J86: Y | L86: n
A87: xv | B87: The system should be configurable to add, delimit, or create new constraints based on regulatory bodies' requirements. 1) During monthly rostering, officer assignment to demand, mass upload, or job reconciliation, a hard stop function should be activated if the officer does not meet the hard constraints. Hard Constraints include: MOM Regulations PLRD Regulations APGD Regulations PWM Regulations Certis Policy (e.g., CDRC) Traffic Police Regulations Examples of constraints: a) Driving/Riding License b) PLRD License Expiry and Notification c) Regulatory Courses (Qualifications captured in SAP) such as: -HCTA/RTT -PGPS -PAGPD -CDRC d) Casino Regulatory Act e) Monthly OT Hours (72 hours) f) Daily Hours (13/14 hours) - system should be configurable g) Monthly Maximum Hours h) Weekly hours/Number of maximum working days for Part-Timers i) D-10 Rest Hours j) Maximum Number of working days - 12 consecutive days k) 1 OFF Day per week l) OFF Day Consent m) Others" 2) Table to maintain soft/hard constraints 3) In built approval process to overide soft/hard constraints 4) Exception Table / Rule Break to input the period to override soft/hard constraints 5) All constraints should be configureable by product type, scheme, employment status (full/part timer), rank & nationality. | C87: Y | D87: Detailed list of applicable contraints with each regulation body would need to be provided and evaluated. | E87: SX | G87: SX | I87: 2a | J87: Y | L87: n
A88: xvi | B88: The system should be capable of assigning and unassigning tasks, managing off days and overtime, creating absence records, splitting demand, and swapping off days | C88: Y | E88: SX | G88: SX | I88: 2a | J88: Y | L88: n
B89: The system should be capable of managing officers deployed to multiple assignments within the same day, such as outrider or outcome-based tasks, all within the working hours | C89: Y | E89: SX | G89: SX | I89: 2a | J89: Y | L89: n
B90: The system should be capable of managing redeployment across different sites and handling changes in officer deployment | C90: Y | E90: SX | G90: SX | I90: 2a | J90: Y | L90: n
B91: The system should be capable of managing redeployment across the BU Share pool and internal business units | C91: Y | E91: SX | G91: SX | I91: 2a | J91: Y | L91: n
B92: The system should have a logic to identify officers who are required to perform overtime after their rostered hours. For example, it should monitor utilization over a 72-hour period. Create a exemption table to allow by employee group, product type and Scheme (pay scale group) to be maintain for their overtime. | C92: Y | D92: Need specific information on how this wants to be handled. We have all the components necessary, but workflow may require an extension. | E92: SX | G92: SX | I92: 2a | J92: Y | L92: n
B93: The system should provide an alert if an officer is about to exceed a specified number of hours | C93: Y | E93: X | G93: N | I93: 2a | L93: n
B94: The system should include a monitoring dashboard for deployment status, featuring alerts and call-to-action functions, such as a configurable shortfall dashboard | C94: Y | E94: X | G94: X | H94: Deployment dashboard is required Call to action is optional | I94: 2a | J94: Y | L94: n
B95: The system should have a feature to recommend officers who are either (i) qualified and available or (ii) qualified but currently deployed to cover a shortfall. Once approved, the system should send a notification to the officer. | C95: Y | E95: SX | G95: SX | I95: 2a | J95: Y | L95: n
B96: The system should include a built-in approval system to override constraints and automatically assign officers to meet demand | C96: Y | E96: X | G96: SX | H96: Workflow Approval System | I96: 2a | J96: Y | L96: n
B97: The system should read through consent data and enforce limitations on changing off days or assigning overtime if the officer has not provided consent | C97: Y | D97: Consent is captured in the employee profile but if explicit ad-hoc consent is needed per action, this needs to be mapped out and would be an extension as part of the implementation. | E97: SX | G97: N | H97: Integrate with Optimax (Time in Time out system) | I97: 2a | L97: n
B98: The system should process split demand APO with an additional 30 minutes at the start and end of the shift. The G4-Tolerance setting should ensure that this does not conflict with training attendance, preventing any porting failures | C98: Y | D98: Need explicit flow of what this means along with expected outcomes and behaviors in the system. | E98: SX | G98: SX | I98: 2a | J98: Y | K98: Don't recall covering this case during the starter kit. Would need a reminder of what this entails. Putting "Yes" as it seems like if there is split demand for an APO, it would entail not causing issues with training tasks when it comes to the 30min tolerance at start and end. | L98: n
B99: The system should be capable of managing night shifts, such as from 10 PM to 10 AM, and handling ad-hoc assignments, for example, from 2 AM to 3 AM | C99: Y | E99: SX | G99: SX | H99: Previous Day Indicator for Night Shift | I99: 2a | J99: Y | L99: n
B100: The system should include the following functionalities: 1) A shared personnel pool function to utilize officers from other departments. For example, BU A officers should be able to support BU B assignments and BU B should be able to assign BU A officers to meet demand. 2) The ability to assign officers who are not mapped in the system. For instance, BU C officers should be able to support BU B assignments, and BU B should be able to assign BU C officers to meet demand, even though BU C currently does not utilize the NGRS System. 3) A feature to create off days and unplanned absences for multiple IDs. 4) The capability to amend officer status from work to off, off to work, off to off-day overtime, and off to unplanned absence. 5) While performing manual toggling, the system should display the officers' existing assignments. 6) Once an officer has been assigned to a task, the system should not allow the removal of the officer from the demand. | C100: Y | D100: Point 2 needs to be further explained. A user cant be assigned if they don't exist. Point 6, extension needed to prevent unassignmnent and would need to know if this is overridable. | E100: SX | G100: SX | H100: 1 - N (Recon with eJobcard) 2 - N (Recon with eJobcard) 3 - SX 4 - SX 5 - SX 6 - SX | I100: 2a | J100: Y | L100: n
...

Sheet 2b. Planning
A1: 2b. | B1: Planning. In terms of functionalities in the roster design and forecasting, the Software shall: | C1: Fulfil Certis' Requirements? (Yes/No/Partial) | D1: Remarks | E1: SG (X if required SX Showstopper) | F1: AU (X if required) | G1: Revised Requirements | H1: Certis Remarks | I1: Indicator | J1: Response (Yes/No/Partial) | K1: Remarks | L1: Cadence Related
A2: i. | B2: Roster Forecasting.
B3: The solution must able to generate roster patterns that optimise cost-efficiency while ensuring full compliance with applicable industrial instruments | C3: Y | D3: More specific information is necessary. High likelyhood that a tailored model along with tailored integration for input parameters is needed. | E3: SX | F3: X | G3: SX | H3: No need Cost efficiency. Regulatory Requirement is a must | I3: 2b | J3: Y | K3: Can do roster creation and validate that all rosters are compliant. Any non-compliance will be flagged by the system and can be handled by the planners. | L3: n
B4: The solution must dynamically adjust workforce schedules based on forecasted demand (i.e. passenger throughput at a screening point). The system must ensure compliance with all relevant labor regulations and support the creation of cost-effective, efficient rosters that maintain high service standards during varying demand periods. | C4: Y | D4: More specific information is necessary. High likelyhood that a tailored model along with tailored integration for input parameters is needed. | E4: SX | F4: X | G4: X | H4: Regulatory Requirement is a must | I4: 2b | J4: Y | K4: Same as above | L4: n
B5: The solution must enable forecasting of workforce coverage by assessing resource availability for future dates. This should include consideration of approved leave, projected headcount, and historical absenteeism trends to ensure adequate staffing and operational continuity. | C5: Y | D5: More specific information is necessary. High likelyhood that a tailored model along with tailored integration for input parameters is needed. | E5: SX | F5: X | G5: X | H5: Regulatory Requirement is a must | I5: 2b | J5: Y | K5: Same as above | L5: n
A6: ii. | B6: Standard Roster Types | F6: X
B7: The solution must support the creation and management of configurable roster templates to accommodate a range of operational needs, including rotating shift patterns, demand-driven schedules, standard business weeks, and event- or project-based deployments. | C7: Y | E7: SX | G7: SX | I7: 2b | J7: Y | L7: n
A8: iii. | B8: Special Roster Types | F8: X
B9: Include capability to create unique roster types:
B10: Multi Chain Pattern - Multi Chain Roster Patterns are a specific type of Roster Model that allows employees to switch rosters based on planned demand or workload requirements. This Roster Model is designed to account for fluctuating coverage requirements from week to week. The Multi-Chain Roster is composed of one or more “demand” rosters, that once built allows for employees to switch throughout each roster based on a defined date driven basis. This design allows for:
B11: 1. Efficient control of employee movement between rosters | C11: Y | E11: SX | G11: SX | I11: 2b | J11: Y | L11: n
B12: 2. Automatic activation/de-activation of Roster Patterns based on defined dates | C12: Y | E12: X | G12: X | I12: 2b | J12: Y | L12: n
B13: 3. This allows multiple child/sub rosters to be attached to a single master roster. These rosters can then be date triggered based on varying demand. Personnel inherit the same line number in the roster when switching child rosters. | C13: Y | D13: Need documented process. May require extension. | E13: SX | G13: SX | H13: Split Shift | I13: 2b | J13: Y | L13: n
B14: 4 The solution must support advanced rostering models that enable flexible scheduling in response to variable demand patterns. The system must allow automatic activation or deactivation of roster patterns based on planned operational demand. The solution must enable planners to create optimised rosters that meet operational requirements while minimising labour costs. It should support various workforce types including part-time, casual, resource contractors, and support flexible options such as split shifts. The solution must support rostering across multiple cost centres, allowing resource sharing and optimisation across business units to improve workforce utilisation. | C14: Y | D14: Need documented process. May require extension. | E14: SX | G14: SX | I14: 2b | J14: Y | L14: n
A15: iv. | B15: Cost Minimization through Roster Design
B16: Flexible scheduling – allow Roster Planners various scheduling options including Split Shifts, Part–time work, Resource Contractors, to fill rosters with the lowest cost possible. | C16: P | D16: Need documented process. May require extension. | E16: X | G16: X | H16: Split Shift cost not required | I16: 2b | J16: Y | K16: Split shift no problem, cost optimization adds overhead. As mentioned in the Certis remarks, it is not considered as part of this requirement. That being said, we are currently looking at a way to add cost optimization without affecting performance. | L16: n
A18: v. | B18: Business Workflows
B19: Rule Breaks in Planning – include pre-built and customizable workflows for fatigue and skill rule break handling, with both in-application notifications and email-based notifications for rule break approval processes. | C19: Y | D19: Need documented process. May require extension. | E19: SX | G19: SX | I19: 2b | J19: Y | L19: n
A21: vi. | B21: Special Roster Rules
B22: 1. Fatigue rules
B23: (a) Mandatory rest period between rostered shifts (fatigue rules) – capability to configure a rule of minimum hours of rest between rostered shifts (e.g. 8 hours from end of Shift 1 to start of Shift 2) | C23: Y | E23: SX | G23: SX | I23: 2b | J23: Y | L23: n
B24: (b) Limit maximum working hours per cycle (fatigue rules) . - e.g. no more than 60hrs per week. Special rules apply to employee groups e.g. Students, seasonal. In other words, enforce mandatory rest day within a work period (e.g. 1 rest day per 7 days). | C24: Y | E24: SX | G24: SX | I24: 2b | J24: Y | L24: n
B25: (c) Limit consecutive rostered days (fatigue rules) – capability to configure a rule to limit consecutive rostered days (e.g. maximum of 7 consecutive rostered days) | C25: Y | E25: SX | G25: SX | I25: 2b | J25: Y | L25: n
B26: (d) Limit maximum Overtime (fatigue rules) – capability to l imit the maximum hours of work to 60hrs per week, or an average of multiples of 60hrs based on Roster Cycle, i.e. 120hrs over 2-week cycle, 180hrs over 3-week cycle, 240hrs over 4-week cycle or 480hrs over an 8-week cycle. | C26: Y | E26: SX | G26: SX | I26: 2b | J26: Y | L26: n
B27: (e) Fatigue rules shall be configured to apply to a specific group of personnel (e.g., in Singapore daily max 13 hours for scheme B and 14 hours for scheme A) | C27: Y | E27: SX | G27: SX | I27: 2b | J27: Y | L27: n
B28: (f) The solution must enforce configurable fatigue management rules. | C28: Y | E28: SX | G28: SX | I28: 2b | J28: Y | L28: n
B29: 5. Unpredictability rules – can automatically fill a roster by selecting one or more employees per product type (e.g. armed guard, service concierge), to form a team assigned to a Task. The following rules shall apply:
B30: (a) no officer shall be rostered with the same Team for more than 1 day consecutively. | C30: P | D30: Need documented process. May require extension. | E30: X | G30: N | H30: To integrate with MASS+ | I30: 2b | L30: n
B31: (b) no officer shall be rostered to the same should be on same demand for more than 1 day consecutively. | C31: Y | E31: X | G31: N | H31: To integrate with MASS+ | I31: 2b | L31: n
B32: 6. Rostering Reserve/Relief employees to fill billable demands – have the capability to automatically roster reserve/relief group of employees into multiple unfilled billable demands without impact on the original reserve/relief shift pattern. | C32: Y | E32: SX | G32: X | H32: Manual Toggle | I32: 2b | J32: Y | L32: n
B33: 7. Split rosters across multiple Cost Centres – have the capability to allow rosters to split across multiple Cost Centres, to allow cross-rostering of employees from one Cost Centre to another to maximise manpower availability. | C33: Y | E33: SX | G33: SX | I33: 2b | J33: Y | L33: n
B34: 8. Blacklist/Whitelist can blacklist/whitelist at various administrative levels e.g., demand/work type, site, client. | C34: Y | D34: Need an extension for blacklisting/whitelisting of specific resources based on defined criteria. | E34: SX | G34: SX | I34: 2b | J34: Y | L34: n
B35: 9. Hard-protect roster slot s. Ensure that shifts which were assigned based on Shift Swap or Self-Bid methods are NOT subject to change when the roster is re-generated. These slots are protected from any automatic change. | C35: Y | E35: SX | G35: SX | H35: Integrate with Cadence | I35: 2b | J35: Y | L35: Y | M35: Cadence
B36: 10. Ability to apply Global Changes according to one or more attributes e.g. change shift pattern of all employees belonging to a single product/Position/level type. | C36: Y | E36: SX | G36: SX | I36: 2b | J36: Y | L36: n
B37: Demand Creation | C37: Fulfil Certis' Requirements? (Yes/No/Partial) | D37: Remarks
A38: i. | B38: Please provide a detailed description of the various types of demand within the Workforce Scheduling (NGRS) system. | C38: Y | D38: Demand can be created ad-hoc, repeating and through integration. The types of demand are unlimited as the demand can be tagged with customizable and/or definable labels to categorize it. There is no limit on the "types" of demand within the system. | E38: X | G38: N | H38: Just show E2E process only | I38: 2b
A39: ii | B39: Please outline the end-to-end process for configuring new demand within the Workforce Scheduling (NGRS) system, including but not limited to parameters such as 24/7 operations, allowances, time, headcount, gender, nationality, and skillsets | C39: Y | D39: When demand is created, can have restrictions or mandatory qualification issued with that demand. | E39: X | G39: N | H39: Just show E2E process only | I39: 2b
A40: iii. | B40: The system must have functionality that allows for the creation of backdated work orders, including the ability to create and send them for billing within a 24-hour timeframe | C40: Y | E40: SX | G40: SX | I40: 2b | J40: Y | L40: n
A41: iv. | B41: Please specify the duration for which the roster allows updates to backdated entries | C41: Y | D41: Limits can be put based on Certis' needs. | E41: SX | G41: SX | I41: 2b | J41: Y | K41: Limits can be put based on Certis' needs. | L41: n
A42: v | B42: The system must support the capability to accommodate last-minute changes and ensure updates are reflected within the same day. | C42: Y | E42: X | G42: X | I42: 2b | J42: Y | L42: n
A43: vi | B43: The system must support the functionality that allows for duplicating existing demand, including the ability to insert a validity date. | C43: Y | E43: SX | G43: SX | I43: 2b | J43: Y | K43: Don't recall wht a "validity date" is but likely not complex enough to change the response from "Yes". | L43: n
A44: vii | B44: The system must support the configuration of constraints and allowances with validity dates to ensure they are applied correctly within the specified time frames | C44: Y | E44: SX | G44: SX | I44: 2b | J44: Y | K44: In this case it seems like validity date means effective date. | L44: n
A45: viii | B45: The system must support the functionality that allows users to indicate whether a roster entry is PLRD payable at the demand level. | C45: Y | E45: SX | G45: SX | H45: APO. Tagging System to handle | I45: 2b | J45: Y | L45: n
A46: ix | B46: The system must support the filter functionality that allows the system to generate reports indicating PLRD payments | C46: Y | E46: SX | G46: SX | H46: Allow Tagged Demands in to a report | I46: 2b | J46: Y | L46: n
A47: x | B47: The system must support the functionality that allows users to view, edit, and copy expired work orders. | C47: Y | E47: SX | G47: SX | I47: 2b | J47: Y | L47: n
A48: xi | B48: The system must support the functionality that allows constraints, allowances, and coverage to be applied to multiple selected work order line items. | C48: Y | E48: SX | G48: SX | I48: 2b | J48: Y | L48: n
A49: xii | B49: The system must support the functionality that allows for the grouping of applicable constraints. | C49: Y | E49: SX | G49: SX | I49: 2b | J49: Y | L49: n
A50: xiii | B50: The system must support the functionality that allows users to create templates for constraints and allowances. | C50: Y | E50: SX | G50: SX | I50: 2b | J50: Y | L50: n
A51: xiv | B51: The system must support the functionality to differentiate between billable and non-billable demand for clients. | C51: Y | E51: SX | G51: N | H51: Tagging System to handle | I51: 2b | L51: n
A52: xv | B52: The system must support the functionality to differentiate between billable demand on permanent and ad-hoc contracts, with view-only access | C52: Y | E52: SX | G52: N | H52: Tagging System to handle | I52: 2b | L52: n
A53: xvi | B53: The system must support the functionality to differentiate demand based on product type and rank | C53: Y | E53: SX | G53: SX | I53: 2b | J53: Y | L53: n
A54: xvii | B54: The system must support the functionality to differentiate between headcount-based and outcome-based demand | C54: Y | E54: SX | G54: N | H54: Tagging System to handle | I54: 2b | L54: n
A55: xviii | B55: The system must support the functionality to allow users to identify non-billable demand as buffer demand, on-the-job training (OJT) demand, training demand, or New Hire Induction (NID) | C55: Y | E55: X | G55: N | H55: Tagging System to handle | I55: 2b | L55: n
A56: xix | B56: The system must support the functionality to allocate cost centers to created demand. | C56: Y | E56: X | G56: X | H56: Tagging System to handle SF needs to be able to extract the hashtagged demands | I56: 2b | J56: Y | L56: n
A57: xx | B57: The system must support the functionality to allow the sharing of a pool across different business units (BUs) and supports backdating up to 48 hours, including the ability for users to set a validity date for the shared pool. | C57: Y | E57: SX | G57: N | H57: Daily Recon, integrate with SF | I57: 2b | L57: n
A58: xxi | B58: The system must support the functionality to automatically create demand with an inbuilt approval system, specifically for On-the-Job Training (OJT), SO Perspective, and Outrider. | C58: Y | E58: X | G58: N | I58: 2b | L58: n
B59: The system must support the functionality to have the demand tolerance functionality that allows users to set travel parameters based on plant level, customer, demand, officer ID level, and product type | C59: Y | D59: Need documented process. May require extension. | E59: SX | G59: SX | I59: 2b | J59: Y | L59: n
B60: The system must support the functionality to identify the business unit (BU), segment, or division to which a specific demand belongs, including functionality that allows users to self-group officers. | C60: Y | E60: SX | G60: SX | I60: 2b | J60: Y | L60: n
B61: The system must support the functionality that allows users to group roster entries | C61: Y | E61: SX | G61: SX | I61: 2b | J61: Y | L61: n
B62: The system must support the functionality that allows tagging of roster entries with details such as geo-fencing, facial recognition of assignments, addresses, and grouping of assignments across multiple sites. | C62: Y | E62: X | G62: X | H62: Integrate with Optimax | I62: 2b | J62: Y | L62: n
B63: The system must support the functionality of the system that allows users from Business Unit A to view and amend demand from Business Unit B, including the ability to share roster functions if required | C63: Y | E63: SX | G63: N | I63: 2b | L63: n
B64: The system must support the functionality that restricts CRP (resource partner) users to view only their own roster, unless additional permissions are granted | C64: Y | E64: SX | G64: N | H64: Integrate RCMS via API | I64: 2b | L64: n
B65: The system must support the functionality that allows for the creation of last-minute (day-of-operations) demand | C65: Y | E65: SX | G65: SX | I65: 2b | J65: Y | L65: n
B66: The system must support the functionality that provides alerts for newly published or expiring demand, such as through email or Argus notifications | C66: Y | E66: X | G66: X | H66: Notifications can be via NGRS Manager App | I66: 2b | J66: Y | L66: n
B67: The system must support the functionality that allows for the amendment of existing demand, including changes to allowances, shift patterns, rank, and coverage | C67: Y | E67: SX | G67: SX | I67: 2b | J67: Y | L67: n
B68: The system must support the functionality that allows for the creation and amendment of backdated demand | C68: Y | E68: SX | G68: SX | I68: 2b | J68: Y | L68: n
B69: The system must support the functionality that allows demand to be filtered or separated based on criteria such as skillsets, regulatory minimum requirements, or contractual obligations (e.g., 1 in 10 employees must hold a specific license) | C69: Y | E69: X | G69: X | I69: 2b | J69: Y | K69: Would need to know the list of "contractual obligation" types/possibilities. | L69: n
B70: The system must support the functionality that enables the system to automatically tag mandatory constraints based on product type and skill set (e.g., rider) during the creation of demand | C70: Y | E70: X | G70: X | H70: Tag with Basic Constraints | I70: 2b | J70: Y | L70: n
B71: The system must be capable of managing unplanned changes to permanent assignments, such as changes in location, duty post, or shift timing for a particular date | C71: Y | E71: SX | G71: SX | I71: 2b | J71: Y | L71: n
B72: The system must include an identifier to determine the Tier level of sites | C72: Y | E72: X | G72: N | H72: Tagging System to handle | I72: 2b | L72: n
B73: The system must support the functionality that allows the assignment of an operations unit in charge by plant, planner group, and demand for reporting purposes | C73: P | D73: Need documented process. May require extension. | E73: X | G73: X | H73: Auto sending of reports to relevant supervisor | I73: 2b | J73: Y | K73: Auto sending of reports to relevant supervisor | L73: n
B74: The system must support the functionality that allows users to create a single billable contract covering multiple locations. | C74: Y | E74: SX | G74: SX | I74: 2b | J74: Y | L74: n
B75: The system must support the functionality to handle outcome-based, utilization-based, recurring, and ad-hoc demands | C75: Y | E75: SX | G75: SX | H75: Adhoc Demands Only | I75: 2b | J75: Y | K75: Agreed with Certis remarks. Other type of demand will be sent to WorkAxle via integration. | L75: n
B76: The system must support the functionality that provides training schedule validation, including hours achieved, overtime, and fatigue management, and its synchronization with SAP. | C76: Y | E76: SX | G76: SX | I76: 2b | J76: Y | L76: n
B77: The system must support the functionality that allows for automated team formation based on predefined rules, such as skill sets, the number of staff per team, regulatory compliance, and frequent rotation of team members | C77: Y | E77: SX | G77: N | H77: Integrate with MASS+ | I77: 2b | L77: n
B78: Scalable/Customisable Priority listing for demands. I.e When booking for training demand to 'override working demand/off day" | C78: Y | D78: Need documented process. May require extension. | E78: SX | G78: SX | H78: integrate with LTMS & S4 Training takes priority. Allow manual overide/amendment | I78: 2b | J78: Y | K78: Agreed with Certis remarks. | L78: n | M78: LTMS
B79: Allow customisable demands for both billable and non-billable demands which is translatable to billing, scalable to create whole month or individual demand | C79: Y | E79: SX | G79: N | H79: Tagging System to handle | I79: 2b | L79: n
B80: Roster timing able to amend base on client requirement on daily basis.Refer to dynamic rostering | C80: Y | E80: SX | G80: SX | H80: Allow amendment in timing | I80: 2b | J80: Y | K80: Agreed with Certis remarks. | L80: n
B81: Rostering Logic | C81: Fulfil Certis' Requirements? (Yes/No/Partial) | D81: Remarks
A82: i. | B82: The system must validate all scheduled training against regulatory requirements and overtime constraints to ensure compliance before deployment. | C82: Y | D82: Potential extensions as part of our planning algorithm. | E82: SX | G82: SX | I82: 2b | J82: Y | K82: When auto-rostering takes place, can make it that scheduled training is not overwritten and that everything follows regulatory requirements. | L82: n
A83: ii | B83: The system must ensure that staff receive at least one rest day per week and must not work more than 12 consecutive days within a two-week period. | C83: Y | E83: SX | G83: SX | I83: 2b | J83: Y | L83: n
A84: iii. | B84: The system must support the configuration of maximum working hours per day based on employee groups and product types, with the ability to differentiate by different schemes or product types | C84: Y | E84: SX | G84: SX | I84: 2b | J84: Y | L84: n
A85: iv. | B85: The system must support the calculation of 72-hour overtime methodology for different schemes or product types. | C85: Y | E85: SX | G85: SX | I85: 2b | J85: Y | L85: n
A86: v | B86: The system need to ensure compliance with Auxiliary Police Officer (APO) APGD D10 (Regulatory) by mandating a minimum of 8 hours of rest between each working shift. *Police Licensing and Regulatory Division (PLRD), Police Force Act(PFA) and Auxiliary Police General Directive (APGD). | C86: Y | D86: Potential extensions as part of our planning algorithm. | E86: SX | G86: SX | I86: 2b | J86: Y | L86: n
A87: vi | B87: The system must ensure the definition of a shift must align with S4 HANA standards, such as 0001 to 2359 or specific shifts like 8pm to 8am | C87: Y | E87: SX | G87: N | H87: Align with SF/ S4 | I87: 2b | L87: n
A88: vii | B88: The system must support the Employee Group Flexi is provided with a minimum of 1 hour of rest between shifts. To provide Employee Group Flexi an option if to deduct a minimum 1hr of rest between shift. | C88: Y | E88: SX | G88: SX | I88: 2b | J88: Y | L88: n
A89: viii | B89: The system must support automatic roster splitting when switching from roster 1 to roster 2 | C89: Y | E89: SX | G89: SX | I89: 2b | J89: Y | L89: n
A90: ix | B90: The system must support the specify allowances based on product type, employee group, and scheme within the same demand/roster | C90: Y | E90: SX | G90: SX | I90: 2b | J90: Y | L90: n
A91: x | B91: The system must support the implementation of the daily and weekly checks to ensure that resignees are removed from the roster and demand. | C91: Y | E91: SX | G91: SX | I91: 2b | J91: Y | L91: n
A92: xi | B92: The system must support to ensure that any changes to officer or roster timings made mid-month are consistently applied to subsequent days. | C92: Y | E92: SX | G92: SX | I92: 2b | J92: Y | L92: n
A93: xii | B93: The system must support allowance configuration that calculates allowances on an hourly basis, such as working hours. | C93: Y | E93: SX | G93: N | H93: Tag Paycode & send hours worked to SF/S4 for payment SF/S4 does time Eval & Payroll | I93: 2b | L93: n
A94: xiii | B94: The system must support allowance approval process that requires certain roles to approve allowances. These roles should also have the capability to archive unwanted or expired requests | C94: Y | D94: Need documented process. May require extension. | E94: SX | G94: SX | I94: 2b | J94: Y | K94: Yes as was described in startkit. | L94: n
A95: xiv | B95: The system must support customizable rostering logic, allowing for different overtime hour calculations for schemes A and B, as well as distinguishing between contractual hours and overtime hours. | C95: Y | E95: SX | G95: SX | I95: 2b | J95: Y | L95: n
A96: xv | B96: The system must support that roster and time evaluation are consistent, including substitution (work schedule rule). | C96: Y | E96: SX | G96: N | H96: Time Eval & Subsitution done in SF/S4 | I96: 2b | L96: n
A97: xvi | B97: The system must support Flexi and part-time employees must adhere to different regulatory rules, such as not working more than 3 days or 12 hours per week, and not exceeding 35 hours per week (e.g., 6 days at 4 hours each) | C97: Y | E97: SX | G97: SX | I97: 2b | J97: Y | L97: n
A98: xvii | B98: The system must allow bypassing regulatory or contractual requirements if the exception table is updated. Updates to the exception table must be routed for approval | C98: Y | D98: Need documented process. May require extension. | E98: SX | G98: SX | I98: 2b | J98: Y | L98: n
A99: xviii | B99: For Flexi and part-time employees, if they work more than the regulatory hours, the system should be able to generate a report comparing actual hours worked against regulatory hours. The excess hours should be automatically populated into an incentive and paid to the staff | C99: Y | E99: SX | G99: SX | I99: 2b | J99: Y | L99: n
A100: xix | B100: The system must allow for OFF Day Consent. If consent is not given, users will not be permitted to swap their off days. There should also be an option to select the year. | C100: P | D100: Need documented process. May require extension. | E100: X | G100: N | H100: Integrate w/ Optimax | I100: 2b | L100: n
A101: xx | B101: The system must allow Flexi employees to book jobs in advance and automatically prompt them to acknowledge if they exceed the allowed hours, which may be subject to incentives | C101: P | D101: Need documented process. May require extension. | E101: X | G101: N | H101: Integrate with Cadence | I101: 2b | L101: Y | M101: Cadence
A102: xxi | B102: The system must allow for configurable meal break hours, such as providing a 1-hour meal break for every 10 hours worked. | C102: Y | E102: SX | G102: N | H102: Time Eval & Subsitution done in SF/S4 | I102: 2b | L102: n
...

Sheet 2c. Delivery
A1: 2c. | B1: Delivery. In terms of delivering filled rosters and supporting day-of-ops, the Software shall: | C1: Fulfil Certis' Requirements? (Yes/No/Partial) | D1: Remarks | E1: SG (X if required SX Showstopper) | F1: AU (X if required) | G1: Revised Requirements | H1: Certis Remarks | I1: Indicator | J1: Response (Yes/No/Partial) | K1: Remarks | L1: Cadence Related
A2: i. | B2: Basic Scheduling Capabilities | F2: X
B3: The solution must support the creation, modification, and publication of employee rosters for individuals or groups across multiple operational units with varying business rules. It must accommodate updates to draft or published rosters over different timeframes (e.g., from a specific date onward or for a defined period) to maintain flexibility and operational continuity. | C3: Y | E3: SX | G3: SX | I3: 2c | J3: Y | L3: n
B4: The system must support the creation and assignment of both simple and complex work patterns. These patterns should be applicable to individual employees or groups, with flexibility to accommodate varied roles, sites, or classifications. | C4: Y | E4: SX | G4: SX | I4: 2c | J4: Y | L4: n
B5: The solution must provide visibility into forecasted demand, roster shortfalls, and unallocated shifts, enabling proactive workforce planning and timely resolution of coverage gaps. | C5: Y | D5: When viewing the roster, visual notifications are displayed for open slots, and messages are displayed below the roster showing how many slots were created and filled. | E5: SX | G5: SX | I5: 2c | J5: Y | L5: n
B6: The system must support the generation of cost-effective rosters by forecasting roster costs, including allowances, loadings, and overtime. It should promote fair and equitable distribution of work hours across the workforce, ensuring minimum target hours are met while reducing reliance on overtime. Where applicable, the system should highlight scheduling options with or without rule breaks to support informed decision-making. | C6: Y | E6: X | G6: X | I6: 2c | J6: P | K6: Some elements are included here, but proactive costing before rosters are created creates an exponentially complex problem to solve while keeping the software fast. Roster costing is usually once roster is assigned and/or published, not beforehand. | L6: n
B7: The solution must support rule-driven automation for shift allocation, considering factors such as skills, availability, cost, qualifications, hours worked, and policy compliance. It should allow prioritisation of best-fit candidates for each shift based on configurable criteria. | C7: Y | E7: SX | G7: SX | I7: 2c | J7: P | K7: Same as above, cost inclusion during this process (especially since there are such a volume of compliance rules and categories, becomes an exponentially large problem space to solve). Most of the other elements are taken into account, but cost is challenging while keeping the solution optimized for speed. As technology advances, this will likely change and machines will likely be able to solve larger problem spaces in a shorter amount of time. | L7: n
B8: Create and assign work patterns to an individual employee or to a group of employees in mass (e.g., to all officers at the same site) | C8: Y | E8: SX | G8: SX | I8: 2c | J8: Y | L8: n
B9: Auto assign work patterns from an interface The solution must support the import and update of rosters via external sources (e.g., spreadsheets or third-party systems), allowing flexibility in how rosters are created or maintained. | C9: Y | D9: Work patterns can be assigned on logging into our solution from your PC, Laptop or tablet | E9: X | G9: X | H9: Allow Mass Upload | I9: 2c | J9: Y | L9: n
B10: The system must provide real-time notifications to roster planners for actions such as unallocated shifts, absences, no-shows, and policy violations (e.g., overtime breaches), supported by configurable workflows for approvals or overrides | C10: Y | D10: The ability to manage baseline staffing requirements is supported in SAP F&S by defining staffing headcount requirements and shifts into models. | E10: X | G10: X | I10: 2c | J10: Y | K10: Not exactly notifications but visual indicators and clear visuals that ensure that everything remains compliant. Functionally achieving the same thing. The issue with notifications at volume is that they become overwhelming and users suffer from "notification fatigue" where they no longer pay attention to them. | L10: n
B11: 11. Optimize schedules to reduce overtime and fill unplanned gaps with qualified employees. | C11: Y | E11: X | G11: X | I11: 2c | J11: Y | L11: n
B12: The system should enable automated call-outs or shift offers, using preferred contact methods (e.g., phone, SMS, email), and apply defined criteria such as skill match, availability, cost, and fatigue to ensure rapid, compliant shift filling. | C12: Y | D12: Shift-bidding functionality permits this. May require minor extension. | E12: X | G12: N | H12: Integrate with Cadence & RCMS Via API | I12: 2c | L12: y | M12: cadence
B13: 13. Generate call-out lists based on skills, costs, and fitness for duty and automatically contacts employees via their preferred contact method (phone, email, and/or text message). | C13: Y | D13: Employees are notified through email and/or push notifications | E13: X | G13: N | H13: Integrate with Cadence & RCMS Via API | I13: 2c | L13: y | M13: cadence
B14: 14. Allows unlimited call-out lists. | C14: Y | E14: X | G14: N | H14: Integrate with Cadence & RCMS Via API | I14: 2c | L14: y | M14: cadence
B15: 15. Automatically Identifies the best-fit employees and fill open shifts based on one or more pre-defined criteria, in a prioritized manner to allow Roster Planner to select the best-fit employee | C15: Y | D15: Need documented process. May require extension. | E15: SX | G15: SX | I15: 2c | J15: Y | L15: n
B16: e.g. First by skills-qualified, then by least cost, then by least hours worked. | C16: Y | E16: X | G16: N | H16: Repeated see item 15. | I16: 2c | L16: n
B17: 16. Schedule employees in compliance with overtime rules based on seniority and other complex union requirements. | C17: Y | E17: SX | G17: SX | I17: 2c | J17: Y | L17: n
B18: 17. Prompt/Notify Roster Planner to action on unallocated shifts. | C18: Y | E18: SX | G18: SX | I18: 2c | J18: Y | L18: n
B19: 18. Mark Absent or No Show, where shift is unallocated or reassigned. | C19: Y | E19: SX | G19: SX | I19: 2c | J19: Y | L19: n
B20: The system must enforce qualification and compliance rules at the time of shift execution, not just at the roster creation stage. It must prevent scheduling of unqualified personnel unless a configured exception process (workflow/approval) is in place. | C20: Y | E20: SX | G20: SX | I20: 2c | J20: Y | L20: n
B21: The system must support the configuration and enforcement of business rules and legislative requirements, including those related to fatigue, overtime limits, industrial awards, EBAs, and other employment conditions. Exception handling workflows must be available for managing rule breaks and approvals. | C21: Y | E21: SX | G21: SX | I21: 2c | J21: Y | L21: n
A23: ii. | B23: Other Scheduling Capabilities
B24: 1. Delivery with cost optimisation – in the delivery of rosters and day-of-ops roster adjustments, calculate the forecasted roster costs (inclusive of allowance, loading and overtime) of available options, presenting roster options with and without rule breaks. | C24: Y | D24: Need documented process. May require extension. | E24: X | G24: N | I24: 2c | L24: n
B25: 2. Fair and equitable rostering – include capabilities to manage a fair and equitable roster such that all employees share the available work hours and fulfill the minimum target hours, while minimizing overtime hours. | C25: Y | E25: X | G25: N | I25: 2c | L25: n
B26: 3. Draft Roster Publishing – publish rosters up to 12 months in advance (and select rosters to be published to employees) | C26: Y | E26: X | G26: N | I26: 2c | L26: n
B27: 4. Roster change management – allow draft rosters to be updated in the following ways: | L27: n
B28: (a) Update ALL future rosters | C28: Y | E28: X | G28: X | I28: 2c | J28: Y | L28: n
B29: (b) Update rosters for a specific period ONLY (or from a specific date ONWARDS). | C29: Y | E29: X | G29: X | I29: 2c | J29: Y | L29: n
B30: 5. Manual roster upload – support manual upload of a roster, created via a third party software e.g. Microsoft Excel, in the creation of a new roster and in amending an existing roster. | C30: Y | E30: SX | G30: X | I30: 2c | J30: Y | L30: n
B31: 6. Qualifications. Restrict rostering of personnel without the required qualification(s), with rule break(s) possible with workflow for approval/over-ride. Qualifications rules must be applied on day of shift and not day-of-roster creation. | C31: Y | D31: Need documented process. May require extension. | E31: SX | G31: SX | H31: Repeated for regulatory checks | I31: 2c | J31: Y | L31: n
A32: iii. | B32: Day-of-Ops management – include solutions to manage real-time, day-of-ops activities: | F32: X
B33: 1. Monitoring of time attendance | C33: Y | E33: SX | G33: SX | I33: 2c | J33: Y | L33: n
B34: 2. Re-assignment of unfilled shifts to employees, re-assign OFF Days. | C34: Y | E34: SX | G34: SX | I34: 2c | J34: Y | L34: n
B35: 3. Shift-splitting to maximise workforce availability. | C35: Y | E35: SX | G35: SX | I35: 2c | J35: Y | L35: n
B36: 4. Call-to-action – alerts and notifications to ops planners, with deep-linking of action buttons to actionable pages within the Software. | C36: Y | G36: SX | I36: 2c | J36: Y | L36: n
B37: The solution must support real-time operational management by enabling visibility and responsiveness to workforce activity on the day of operation. It should include capabilities to monitor attendance, reassign shifts or rest days, and optimise workforce deployment through dynamic actions such as shift splitting. The system must provide actionable alerts and notifications with intuitive navigation to relevant functions, supporting timely decision-making and operational continuity. | C37: Y | E37: SX | F37: X | G37: SX | I37: 2c | J37: Y | L37: n
A38: iv. | B38: Special scenarios for time attendance | F38: X
B39: 1/) The solution must support multi-location time tracking, enabling employees to clock in and out at different operational points (e.g., base and work site) as part of a standard workflow, with accurate recording of all attendance events. 2. The solution must support both personal and fixed-site time and attendance options, including mobile devices, clock terminals, desktops, or tablets. Clocking functionality should be accessible in all typical operational environments. 3. The system must support geo-fencing to restrict or validate clocking within designated areas, and include facial recognition or equivalent biometric tools to reduce the risk of fraudulent clocking. 4. The system must provide alternative methods for time capture when primary clocking mechanisms fail, including manual reporting or administrator override, to maintain continuity in time records. | C39: Y | E39: X | G39: X | I39: 2c | J39: Y | L39: n
A40: v. | B40: Frontliner Mobility Solutions(Mobile App) - Work Schedule Management, the software shall have the capability to enable frontline employees to:
B41: 1. View own rosters up to 30 days. | C41: Y | E41: X | G41: X | I41: 2c | J41: Y | L41: y
B42: 2. View own profiles (including qualifications) and update certain fields (e.g. contact number, email). | C42: Y | E42: X | G42: X | I42: 2c | J42: Y | L42: y
B43: 3. Accept or reject additional shifts (bid for shifts) as offered by Roster Planner. | C43: Y | E43: X | G43: N | H43: Integrate with Cadence for shift bidding | I43: 2c | L43: y
B44: 4. View own leave calendar and submit leave day applications (different types of leave days shall be catered for). | C44: Y | E44: X | G44: N | H44: Integrate with Allegro or SF/S4 | I44: 2c | L44: n
B45: 5. View an annual summary of leave, including key totals such as any carryover from prior year, annual entitlement, time off used to date, approved future time off, remaining balance for the year based on all the above, and future time off pending approval. | C45: Y | E45: X | G45: N | H45: Integrate with Allegro or SF/S4 | I45: 2c | L45: n
B46: 6. Indicate availability and work-hour preferences. | C46: Y | E46: X | G46: X | I46: 2c | J46: Y | L46: y
B47: 7. As part of Day-of-Ops, submit absences/unavailability/sick days, with document proof e.g. doctor’s letter. | C47: Y | E47: X | G47: N | H47: Integrate with Allegro or SF/S4 | I47: 2c | L47: y
B48: 8. Initiate and accept employee-to-employee shift swaps (with admin-configurable criteria for swap and auto-approve rules). | C48: Y | E48: X | G48: N | H48: Integrate with Cadence for shift Swapping | I48: 2c | L48: y
A49: vi. | B49: Frontliner Mobility Solutions(Mobile App) - Time Attendance, the software shall have the capability of:
B50: 1. Both personal (mobile) and fixed-site (desktop, clock terminals, mobile tablet) Time and Attendance solutions for all rostered employees to perform clock in-out. | C50: Y | E50: X | G50: X | I50: 2c | J50: Y | L50: y
B51: 2. Employees view own timesheets. | C51: Y | E51: X | G51: X | I51: 2c | J51: Y | L51: y
B52: 3. Facial recognition to mitigate fraud. | C52: Y | E52: X | G52: N | H52: Integrate with Optimax | I52: 2c | L52: y
B53: 4. Geo-fencing constraints of clocking activities to mitigate fraud, employee can be notified or prevented when clocking in/out are outside of a defined area. | C53: Y | E53: X | G53: N | H53: Integrate with Optimax | I53: 2c | L53: y
B54: 5. All solutions to have backup clock in/out reporting function for employees who fail to clock in/out due to e.g., lack of/poor network connectivity, faulty clocking device, forgot own credentials. | C54: Y | E54: X | G54: N | H54: Integrate with Optimax | I54: 2c | L54: y
A55: vii. | B55: Frontliner Mobility Solutions(Mobile App) - Communications, the software shall have the capability of:
B56: 1. Generate and broadcast communications in the system, in text and also in form of file attachments. | C56: Y | E56: X | G56: X | I56: 2c | J56: Y | L56: y
B57: 2. Offers standard survey templates (e.g., employee satisfaction, incident reports, etc.). | C57: P | D57: Need documented process. May require extension. | E57: X | G57: N | I57: 2c | L57: n
B58: 3. Schedule recurring communications as reminders, targeting specific employee groups/rosters. | C58: P | D58: Need documented process. May require extension. | E58: X | G58: N | I58: 2c | L58: n
B59: 4. Record of “read/unread status” of communications send to users. | C59: Y | E59: X | G59: X | I59: 2c | J59: Y | L59: n
B60: 5. Enable re-send/reminders to users with “unread” status of communications sent. | C60: P | D60: In-built chat but no read receipts, but can be added as extension work. | E60: X | G60: N | I60: 2c | L60: n
B61: 6. Maintain a log of all communications. | C61: Y | E61: X | G61: X | I61: 2c | J61: Y | L61: n
A62: viii. | B62: Frontliner Mobility Solutions(Mobile App) - Proof of service, the software shall have the capability of an end-to-end frontline task management service which includes:
B63: 1. A form builder to create forms which will be used to capture task-related information. | C63: Y | E63: X | G63: X | I63: 2c | J63: Y | L63: n
B64: 2. Record of information in the form of text, photos and videos. | C64: Y | E64: X | G64: X | I64: 2c | J64: Y | L64: n
B65: 3. Workforce monitoring – able to monitor location of staff while performing their tasks. | C65: P | D65: Would need to extend beacon functionality to have dashboard of live location tracking with beacons. | E65: X | G65: N | I65: 2c
A66: ix. | B66: The mobile solution must interface 2 way with the roster solution , SAP Employee Central and Operations system so that it enable employees to: | F66: X
B67: 1.View personal rosters and leave calendars | C67: Y | E67: X | G67: X | I67: 2c | J67: Y | L67: y
B68: 2.Indicate availability and work-hour preferences | C68: Y | E68: X | G68: N | H68: Integrate with Cadence | I68: 2c | L68: y
B69: 3.Accept, reject, or bid for offered shifts. | C69: Y | E69: X | G69: N | H69: Integrate with Cadence | I69: 2c | L69: y
B70: 4. Initiate or accept peer shift swaps, subject to configurable rules and approval settings | C70: Y | E70: X | G70: N | H70: Integrate with Cadence | I70: 2c | L70: y
B71: 5.Submit real-time absence notifications (e.g., sick days), including documentation uploads | C71: Y | E71: X | G71: N | H71: Integrate with Allegro or SF/S4 | I71: 2c | L71: n
B72: 6.Submit and manage leave requests across multiple leave types | C72: Y | E72: X | G72: N | H72: Integrate with Allegro or SF/S4 | I72: 2c | L72: n
B73: 7. View leave summaries (e.g., entitlement, usage, carryover, balances) | C73: Y | E73: X | G73: N | H73: Integrate with Allegro or SF/S4 | I73: 2c | L73: n
B74: 8.Update selected personal profile fields (e.g., contact details etc) | C74: Y | E74: X | G74: N | H74: Integrate with Allegro or SF/S4 | I74: 2c | L74: n
B75: Automation | C75: Fulfil Certis' Requirements? (Yes/No/Partial) | D75: Remarks
A76: i. | B76: The system should enable Supervisors to have self-service capabilities, such as a portal for managing and viewing rosters, monitoring deployments, and extracting data on attendance, qualifications, absences, and demand details. | C76: Y | E76: X | G76: X | H76: Manager Portal | I76: 2c | J76: Y | L76: n
A77: ii | B77: The system should include an in-built approval system and a storage system for supporting documents, equipped with OCR functionality. This will facilitate changes in attendance, allowances, constraints overrides, and the creation of demand. | C77: P | D77: Need documented process. May require extension. | E77: X | G77: X | H77: Workflow Approval system. OCR is optional | I77: 2c | J77: P | K77: Yes, but OCR would need to be added if needed. | L77: n
A78: iii. | B78: The system should have an automatic function to create demand and assign officers once approval is given. For example, for internal demand, the approval system should automatically create Sales Orders or Perspective Sales Orders and generate the corresponding demand in NGRS | C78: P | D78: Need documented process. May require extension. | E78: X | G78: X | H78: Workflow Approval system. | I78: 2c | J78: Y | L78: n
A79: iv. | B79: The system should have an automatic function to amend attendance once approval is given, and manage back-payment tracking for changes in attendance. For CLS: Certis Forms, it should integrate time changes and specify who will give approval, addressing any back-payment issues. For CAS, it should ensure back-payment tracking without losing visibility. | C79: P | D79: Need documented process. May require extension. | E79: X | G79: X | H79: Workflow Approval system. | I79: 2c | J79: Y | L79: n
A80: v | B80: The system should have an automatic function to amend demand details once approval is given. For example, allowances should be updated by the demand manager manually in NGRS, Certis Forms, or a designated platform. | C80: Y | E80: X | G80: X | H80: Workflow Approval system. | I80: 2c | J80: Y | L80: n
A81: vi | B81: The system should include a feature or platform that allows officers to acknowledge their attendance, allowances, and rosters. | C81: Y | E81: X | G81: X | H81: Workflow Approval system. | I81: 2c | J81: Y | L81: n
A82: vii | B82: The system should include a call-to-action function, which automates alerts for officers who have not yet checked in or out via TITUS after the planned start and end times | C82: P | D82: Requires extension and integration. | E82: X | G82: N | I82: 2c | L82: n
A83: viii | B83: The system should support automatic data synchronization with third-party systems, such as TITUS, ejobcard, eparcs, and optimax | C83: Y | E83: SX | G83: N | H83: Repeated | I83: 2c | L83: n
A84: ix | B84: The system should include pre- and post-compliance check functions with alert capabilities. This includes alerts for unfulfilled billable demand, expiring qualifications, expiring demand, payable timing exceeding clocked hours, and officers without a roster. These alerts should be available in the form of reports or dashboards | C84: Y | E84: X | G84: X | I84: 2c | J84: Y | L84: n
A85: x | B85: Dynamic Business/Operations Intelligence Dashboard + Data Visualisation + data export and sharing (shortfall kpi, recruitment, total duty, manpower health status, absences, cost, simulation of roster, forecasted manpower required, optimising manpower for mega evants, past and future shortfall, violations) 1) Alert/Notification with call to action feature for the following i. License Expiring (PLRD/Work permit/SFA/AED) ii. Unfulfilled Demand for 1 Duty Post Assignment (i.e. Bank) iii. Failure to clock in for 1 Duty Post Assignment (i.e. Polyclinic) iv. Attendance Discrepancies not resolved by 3 days v. Failure to scan out after x hours vi. Failure to AEMS In/AEMS Out vii. Scan out earlier than contractual time for 01 DP/shift viii.AEMS Out earlier than contractual timing Ix.Titus Out at base before AEMS Out x, New Demand created (Billable/Internal) xi. Demand Expiring (Billable/Internal) xii. Any constraints overriden w/o approval xiii. Breaching the daily max hours/ number of consecutive working days/monthly ot hours Example - Officer already clocked 72 hrs OT hours (achived +foreacasted), alert to be send to SE/OM not to get officer to stand in xiv. Predictive underutilise/overutilise officers: | C85: P | D85: Need documented process. May require extension. | E85: X | G85: X | I85: 2c | J85: P | K85: As mentioned in other requirements, visualizations and dashboards should be a dedicated BI tool / Data warehouse. WorkAxle has all the data and is a dedicated Workforce Management Tool. For in-depth reporting and visualizations, other tools are better suited and can pull all the necessary data from the system. | L85: n
A86: xi | B86: The system should feature Digital Twin Rostering to simulate new roster patterns, determine the required manpower, and identify sources for additional manpower during mega events | C86: Y | D86: Not an explicit "digital twin" but simulations are possible and then user can select the best option. | E86: X | G86: N | I86: 2c | L86: n
A87: xii | B87: The system should feature an AI chatbot that allows users to request or query regarding roster or pay discrepancies, similar to the features available in Certis Forms | C87: P | D87: Possible for roster, but pay information would be in SAP. | E87: X | G87: N | I87: 2c | L87: n
A88: xiii | B88: The system should have the capability to automatically schedule reports, such as validation of overtime and lateness e.g. report for lateness | C88: Y | D88: These can be pulled directly from our system in app or through the API. These can be made polled. | E88: SX | G88: SX | I88: 2c | J88: Y | K88: Same as above. | L88: n
A89: xiv | B89: The system should perform daily checks on officers' qualification validity and automatically remove those whose qualifications are no longer valid | C89: Y | E89: SX | G89: N | H89: Repeated | I89: 2c | L89: n
A90: xv | B90: The system should automatically schedule runs in the roster to update the white list and black list | C90: Y | D90: As mentioned, whitelist and blacklist functionality would need to be an extension. | E90: SX | G90: N | H90: Repeated under 2b Planning VI | I90: 2c | L90: n
A91: xvi | B91: The system should allow for the automatic update of overtime (additional hour) one hour before or after a shift. For example, CLS: certain assignments that will require extension, and CAS: certain rosters that will need this automatic update. | C91: Y | D91: Need documented process. May require extension. | E91: SX | G91: SX | I91: 2c | J91: Y | L91: n
A92: xvii | B92: The system should update roster constraints and notify officers of their current roster constraints and assignments. For example, it should allow constraints templates to be tabulated to the demand with product type and rank | C92: Y | E92: X | G92: X | I92: 2c | J92: Y | L92: n
A93: xviii | B93: The system should generate a Daily Availability Report, which will be sent via email. This report will notify if any staff members remain in an available status without being assigned to any demand | C93: Y | E93: X | G93: X | I93: 2c | J93: Y | L93: n
A94: xix | B94: The system should support mass updates for demand coverage, shift patterns, constraints, headcount, allowances, and shift timings. | C94: Y | E94: SX | G94: SX | I94: 2c | J94: Y | L94: n
A95: xx | B95: Automation with in built approval process 1. Auto creation of internal demand with approval process 2. Auto convert attendance to qualification with approval process 3. Auto tagging/delimit of allowance with approval process 4. Auto adjustment of allowance with approval process 5. Auto configuration/creation of tolerance with approval process. Tolerance to be configurable by product type/Scheme/Plant/Assignment/employment status (part timer/full timer) 6. Auto adjustment/delimit of tolerance with approval process. Tolerance to be configurable by product type/Scheme/Plant/Assignment/employment status (part timer/full timer) 7. Auto Overide of constraint (soft/hard) with approval process by date/month/day range + storage for supporting documents 8. Auto tagging/delimit/creation of constraints with approval process 9. Auto amendment of constraints with approval process 10. Auto adjustment/amendment of attendance with approval process + supporting documents 11. Auto extension of demand with approval process (internal demand) 12. Auto Singular/Mass tagging/changes of shift pattern/contractual timing/allowances/constraints by date/month with approval process 13.Auto Singular/ Mass Delimit Functions for shift pattern/allowance/contractual timing/constraints by date/ month with approval process 14. Approval to create/delimit contraints in the constraints table (hard/soft constraints) | C95: P | D95: Need documented process. May require extension. | E95: X | G95: X | H95: Workflow Approval System | I95: 2c | J95: Y | L95: n
A96: xxi | B96: The vendor should explain how the NGRS system integrates with other systems to process billing. Specifically, how data such as job confirmations (JC), e-jobcards, Certis Forms (absences), physical jobcards and sign-offs, e-PARC, and TITUS Customer Portal views are pushed to the billing team. | C96: Y | E96: SX | G96: N | H96: Repeated | I96: 2c | L96: n
A97: xxii | B97: The NGRS system should be linked to third-party systems that allow customers to acknowledge deployments, such as e-jobcards, ePARCs, and the TITUS admin portal. | C97: Y | E97: SX | G97: N | H97: Repeated | I97: 2c | L97: n
A98: xxiii | B98: The NGRS system should allow for backdated amendments of billing data. For example, it should support demand locks after 48 hours (currently handled through manual billing) and accommodate backdated demands that were not created in time. | C98: Y | E98: SX | G98: SX | I98: 2c | J98: Y | L98: n
A99: xxiv | B99: The NGRS system should have a function to automatically bill third parties, such as PLRD, CRP Agencies, and inter-departmental charges. For example: IDC: Officers (CAS) Process (quotation in MRS for internal billing), new system process (quotation) - e-PIF. PLRD: Fees - data from MRS sent for CO approval and forwarded to PLRD for yearly audit. CRP: TITUS data used to pay CRP deployments. | C99: N | E99: X | G99: N | H99: Repeated. See Demand Creation item xiii | I99: 2c | L99: n
A100: xxv | B100: The system must have the functionality to compile a list of operation and billing dashboards or reports e.g. Billing vs unbilled, shift confirmation, ejobcard status, TITUS shift confirmation, unassigned demands, unconfirm demands, submission of IRIM | C100: Y | D100: Extension | E100: X | G100: N | I100: 2c | L100: n
B101: Synchronisation to IRIMS portal to raise IRIMS if working hours exceed regulatory requirement (MOM/D10). Trigger by Xhrs clock out timing from planned end time | C101: Y | D101: Integration work | E101: X | G101: N | H101: Workflow Approval System | I101: 2c | L101: n
...

Sheet 2d. Reconciliation
A1: 2d. | B1: Reconciliation. In terms of functionalities in verifying employee time attendance, the Software shall: | C1: Fulfil Certis' Requirements? (Yes/No/Partial) | D1: Remarks | E1: SG (X if required SX Showstopper) | F1: AU (X if required) | G1: Revised Requirements | H1: Certis Remarks | I1: Indicator | J1: Response (Yes/No/Partial) | K1: Remarks | L1: Cadence Related
A2: i. | B2: Basic Timesheet Reconciliation Functions
B3: 1. Allows automatic approval of timesheets with no exceptions. | C3: Y | E3: SX | F3: X | G3: SX | I3: 2d | J3: Y | L3: n
B4: 2. Allows comments on timesheets. | C4: Y | E4: X | F4: X | G4: X | I4: 2d | J4: Y | L4: n
B5: 3. Saves original and amended timesheets for a complete audit trail. | C5: Y | D5: Audit Log is available | E5: SX | F5: X | G5: SX | I5: 2d | J5: Y | L5: n
B6: 4. Includes live cost tracking on timesheets. | C6: Y | E6: X | F6: X | G6: X | I6: 2d | J6: Y | L6: n
B7: 5. The solution must capture and display key attendance verification details within timesheets, including check-in and check-out times, facial verification records (photo identification), and geolocation data | C7: Y | E7: X | F7: X | G7: X | I7: 2d | J7: Y | L7: n
B8: 6. Tracks automatic and manual breaks. | C8: Y | E8: X | F8: X | G8: X | I8: 2d | J8: Y | L8: n
B9: 7. Ability to restrict who can perform amendments and what pay codes can be amended. | C9: Y | D9: Need documented process. May require extension. | E9: SX | F9: X | G9: SX | H9: Role based/ Access based | I9: 2d | J9: Y | L9: n
B10: 8. All timesheet changes are tracked for auditing/reporting purposes. | C10: Y | E10: SX | F10: X | G10: N | H10: Repeated. Same as point 3 | I10: 2d | L10: n
B11: 9. Ability to automatically route amended timesheets for approvals as required. | C11: P | D11: Need documented process. May require extension. | E11: X | F11: X | G11: N | H11: Repeated. Workflow approval system | I11: 2d | L11: n
B12: 10. Issues automatic email alerts and configurable escalation reminders for unsubmitted or unapproved timesheets. | C12: Y | D12: In-app display/dashboard of unsubmitted or unapproved timecards. | E12: X | F12: X | G12: N | I12: 2d | L12: n
B13: 11. Customisable overtime approval workflows. | C13: P | D13: Need documented process. May require extension. | E13: X | F13: X | G13: X | I13: 2d | J13: Y | L13: n
B14: 12. Allows authorized users to delegate responsibilities, either temporarily or permanently, to specified user roles (such as a manager or assistant manager). | C14: Y | E14: X | F14: X | G14: X | I14: 2d | J14: Y | L14: n
B15: 13. Ability to verify that timesheet data is complete and correct before being sent to payroll for processing. | C15: Y | E15: SX | F15: X | G15: SX | I15: 2d | J15: Y | L15: n
B16: 14. Ability to securely lock timesheets from additional changes before sending to payroll for processing. | C16: Y | E16: SX | F16: X | G16: SX | I16: 2d | J16: Y | L16: n
B17: 15. Only allows authorized personnel to unlock locked timesheets. | C17: Y | E17: SX | F17: X | G17: SX | I17: 2d | J17: Y | L17: n
B18: Business Requirements added (SG BUs)
B19: The system should include a built-in approval system with OCR capabilities and support for document attachments to automatically amend working hours based on the request. | C19: P | D19: Amendements can be made but would need extension for document submission and storage with potential approval flow with document attached. | E19: X | G19: N | H19: Repeated | I19: 2d | L19: n
B20: The system should be able to automatically push attendance data to a third-party system, even if time evaluation is performed in another system. This should include both automatic synchronization and manual triggers. | C20: Y | D20: Integration work | E20: SX | G20: N | H20: Repeated | I20: 2d | L20: n
B21: The system should provide a platform for officers and supervisors to view and acknowledge their attendance, allowances, and daily status. | C21: Y | E21: X | G21: N | H21: Repeated | I21: 2d | L21: n
B22: The system should include a built-in feature or integration with Certis system that allows officers to flag attendance discrepancies and route them to supervisors for amendment e.g. Certis App/ Outsystem | C22: P | D22: Integration work | E22: X | G22: N | H22: Repeated | I22: 2d | L22: n
B23: The system should include a process for backpayment of allowances and attendance, incorporating an approval workflow and back payment mechanism | C23: Y | D23: Retros can be done and passed over to payroll. | E23: SX | G23: SX | H23: Payroll via SF | I23: 2d | J23: Y | L23: n
B24: The system should include a process for urgent changes, updates, and reconciliation to meet payroll cut-off dates. It should allow for urgent changes and updates within a specified period | C24: Y | E24: X | G24: N | I24: 2d | L24: n
B25: The system should have a process for handling urgent ad-hoc orders when an officer is unable to use the normal time attendance. For example, it should manage scenarios like Certis e-Jobcard, internal demand, or waiting for IRIM creation (backdated work order creation). e.g. A normal scenariro that the staff is deployed in a site that have TITUS IN and will also be deploy for adhoc job that will require e-jobcard sign off from client | C25: Y | E25: SX | G25: SX | I25: 2d | J25: Y | L25: n
B26: The system should be capable of recording the initial clock-in time at the start of a shift (Roster A). Even if there is a shift change (from Roster A to Roster B), it should capture the end shift time from Roster B. Additionally, the system must be able to track each demand allowance. | C26: Y | E26: SX | G26: SX | I26: 2d | J26: Y | L26: n
B27: 1) For job reconciliation for payroll, system should be able to draw data from Titus, AEMS, Gallagher, Eparcs, AtOnce, Argus Log In to pay officers 2) System should be able to reconcile attendance based on first in/last out for officers' who are deployed for multiple assignment within the single shift. 3) System should be able to include the tolerance hours (travelling time) that have been set during the tolerance configuration when tabulating the total payable hours Example: a. Contractual Hours: 0800-2000 Tolerance Set: 30 mins planned start time/30 mins planned end time Clock In/Out: 0745-2045 Payable: 0745 - 2030 b. Contractual Hours: 0800-2000 Tolerance Set: 30 mins planned start time/30 mins planned end time Clock In/Out: 0715-2015 Payable: 0730- 2015 c.Contractual Hours: 0800-2000 Tolerance Set: -1 mins planned start time/1 mins planned end time Clock In/Out: 0815-2015 Payable: 0815- 2000hrs d.Contractual Hours: 0800-2000 Tolerance Set: -1 mins planned start time/1 mins planned end time Clock In/Out: 0715-1945 Payable: 0800- 1945hrs e. Contractual Hours: 0800-2000 Tolerance Set: 0 mins planned start time/ 0mins planned end time Clock In/Out: 0715-1945 Payable: 0800- 2000hrs 3) System to guard the daily max hours and maximum hours for both system/manual reconciliation 4) Remarks field to be made available for user to enter reason why manual reconciliation were performed 5) Status of allowances/attendance reconciliation. 6) System able to update new clocking data from Titus 7) System able to auto confirm the attendance if meet the pre-set parameter. | C27: Y | E27: SX | G27: SX | I27: 2d | J27: Y | L27: n
B28: 1)Tolerance to be configurable by product type/Scheme/Plant/Assignment/employment status (part timer/full timer)/customer/demand item Example: 2 different product type (Full Timer/Part Timer) are assign to the same demand ID but only full timer are entitled for the tolerance hours, system should be able to differentiate the product type and payout the tolerance hours only to Full Timers. 3) System able to maintain tolerance for Report time, muster time, billable start/end time, clocking time, payable start /end time. | C28: Y | E28: SX | G28: SX | I28: 2d | J28: Y | L28: n
B29: For Job reconciliation for billing, the system should be able to draw data for billing from Titus, AEMS, Gallagher, Eparcs, AtOnce, Argus, e-Jobcard, Certis Forms. | C29: Y | D29: Integration work. | E29: SX | G29: N | H29: Repeated | I29: 2d | L29: n
B30: The system should support smart check feature to check their successfully total clock-in/out of the day | C30: Y | D30: Can immediately report on the delta from planned vs actuals. | E30: X | G30: X | I30: 2d | J30: Y | L30: n
B31: Time Evaluation | C31: Fulfil Certis' Requirements? (Yes/No/Partial) | D31: Remarks
A32: i | B32: The system should be able to accommodate different time evaluation logics. For example, Security Officers (SO), Aviation Security Officers (AVSO), Cash & Valuable Security Officers (CVSO), and Expressway Monitoring and Advisory System (EMAS) crew (classified as workmen) may each have distinct time evaluation requirements. | C32: Y | E32: SX | G32: N | H32: Time Eval done in SF/S4 | I32: 2d | L32: n
B33: To be able to optimise rest day OT and limit to 72 hours without incomplete monthly roster for officer(Officer roster to follow by assignment coverage instead of fix shift pattern) | C33: Y | E33: SX | G33: SX | I33: 2d | J33: Y | L33: n
B34: Payroll | C34: Fulfil Certis' Requirements? (Yes/No/Partial) | D34: Remarks
A35: i | B35: The system should be able to update changes in the pay structure, such as the Progressive Wage Model (PWM), Scheme A (for Singaporean or foreigner ranks), Scheme B, part-timers' schemes, and non-time evaluation staff. | C35: Y | E35: SX | G35: N | H35: Time Eval done in SF/S4 | I35: 2d | L35: n
F113: Cathy - can you think how we might do this? The employee could be linked to an agency/contractor using a UDF or home location etc… but per scenario above, if they belong to 2 contractors.. Can we still somehow report which contractor rostered them to the shift? Actual hours worked will be costed per client per contractor. Should be no issues with this requirement.

Sheet 2e. Reporting
A1: 2d. | B1: Reporting. In terms of reporting and visualising rostering data, the Software shall: | C1: Fulfil Certis' Requirements? (Yes/No/Partial) | D1: Remarks | E1: SG (X if required SX Showstopper) | F1: AU (X if required) | G1: Revised Requirements | H1: Certis Remarks | I1: Indicator | J1: Response (Yes/No/Partial) | K1: Remarks | L1: Cadence Related
A2: i. | B2: 1. Include a core reporting suite, which allows users to build customised reports. | C2: Y | E2: X | F2: X | G2: X | I2: 2e | J2: Y | K2: Although WorkAxle has built-in reporting functionality, for complete cross-object and cross-system reporting, it is recommended to use a data warehouse and/or a BI Tool to report on the data in our system. All data can be pulled from our API/GraphQL. | L2: n
B3: 2. Have the capability to schedule the sending of reports to licensed users as well as to any specific email address. | C3: Y | E3: X | F3: X | G3: X | I3: 2e | J3: Y | L3: n
B4: 3. The Software Provider shall include a list of pre-built reports (with the data fields within each report) that can be generated from the Software. | C4: Y | E4: X | F4: X | G4: X | I4: 2e | J4: Y | L4: n
A5: ii. | B5: Data Visualisations and Analytics – The data model is prebuilt and integrated with the solution to minimize configuration effort. The software shall support integration with third party analytics tools (e.g. Tableau, MS Power BI) through APIs and it shall include tools to enable the following data visualisations: | C5: Y | E5: X | F5: X | G5: X | I5: 2e | J5: Y | K5: Although WorkAxle has built-in reporting functionality, for complete cross-object and cross-system reporting, it is recommended to use a data warehouse and/or a BI Tool to report on the data in our system. All data can be pulled from our API/GraphQL. | L5: n
B6: 1. Clock in-out data – including employees clocking in-out at multiple sites, date period selection | C6: Y | E6: SX | F6: X | G6: SX | I6: 2e | J6: Y | L6: n
B7: 2. Utilisation rate – number of hours of an employee’s working period spent as billable hours (in billable demands) | C7: Y | E7: X | F7: X | G7: X | I7: 2e | J7: Y | L7: n
B8: 3. Unfilled Rosters – number of shifts that are unfilled in a roster | C8: Y | E8: SX | F8: X | G8: SX | I8: 2e | J8: Y | L8: n
B9: 4. rostering assignment performance (i.e.: manpower shortfall, unplanned absence) | C9: Y | E9: X | F9: X | G9: X | I9: 2e | J9: Y | L9: n
B10: 5.Unfulfilled demands | C10: Y | E10: SX | F10: X | G10: SX | I10: 2e | J10: Y | L10: n
B11: 6. Time attendance performance (i.e.: no clock in/out) | C11: Y | E11: SX | F11: X | G11: SX | I11: 2e | J11: Y | L11: n
B12: 7. Forecast of OT breaches | C12: Y | E12: SX | F12: X | G12: SX | I12: 2e | J12: Y | L12: n
B13: 8. Forecast of exceeding workforce cost budget | C13: P | E13: X | F13: X | G13: N | I13: 2e
B14: 9.total achieved work hours for the month | C14: Y | E14: SX | F14: X | G14: SX | I14: 2e | J14: Y | L14: n
B15: 10. frontliner with near expiring qualification, certificate, skillsets etc. The system shall produce necessary reports for operational, analytical and audit usage. | C15: Y | E15: SX | F15: X | G15: SX | I15: 2e | J15: Y | L15: n
B16: 11. Manpower forecast to show manpower strength health status against rostering demand and to show if there are any spare manpower for new assignment. This is to allow Business Unit to decide if they can take in more business with the available manpower during the period. | C16: Y | E16: X | F16: X | G16: X | I16: 2e | J16: Y | L16: n
B17: Business Requirements added (SG BUs)
B18: The system should be able to manage consent for changing off days to workdays, such as overrides in NGRS (subjective) and rostering change management. | C18: P | D18: All reports to be evaluated and there are three levels of reporting. For complex multi-object reports, leveraging the API and pulling into a BI tool or datawarehouse for complex reports is industry standard. For in-app reports, we can build but after going through a design workshop and understanding which reports live in-app and which are exported for more complexity. | E18: X | G18: N | H18: Repeated | I18: 2e
B19: Lateness report | C19: Y | D19: All reports to be evaluated and there are three levels of reporting. For complex multi-object reports, leveraging the API and pulling into a BI tool or datawarehouse for complex reports is industry standard. For in-app reports, we can build but after going through a design workshop and understanding which reports live in-app and which are exported for more complexity. | E19: SX | G19: SX | H19: Data to be pull from NGRS | I19: 2e | J19: Y | K19: Data to be pull from NGRS | L19: n
B20: Absence report | C20: Y | D20: All reports to be evaluated and there are three levels of reporting. For complex multi-object reports, leveraging the API and pulling into a BI tool or datawarehouse for complex reports is industry standard. For in-app reports, we can build but after going through a design workshop and understanding which reports live in-app and which are exported for more complexity. | E20: SX | G20: SX | H20: Data to be pull from NGRS | I20: 2e | J20: Y | K20: Data to be pull from NGRS | L20: n
B21: Attendance report (Absences, OT, training hours & work hours) | C21: Y | D21: All reports to be evaluated and there are three levels of reporting. For complex multi-object reports, leveraging the API and pulling into a BI tool or datawarehouse for complex reports is industry standard. For in-app reports, we can build but after going through a design workshop and understanding which reports live in-app and which are exported for more complexity. | E21: SX | G21: SX | H21: Data to be pull from NGRS | I21: 2e | J21: Y | K21: Data to be pull from NGRS | L21: n
B22: Daily hour report | C22: Y | D22: All reports to be evaluated and there are three levels of reporting. For complex multi-object reports, leveraging the API and pulling into a BI tool or datawarehouse for complex reports is industry standard. For in-app reports, we can build but after going through a design workshop and understanding which reports live in-app and which are exported for more complexity. | E22: SX | G22: SX | H22: Data to be pull from NGRS | I22: 2e | J22: Y | K22: Data to be pull from NGRS | L22: n
B23: Off Day Consent Report (Regulation) | C23: Y | D23: All reports to be evaluated and there are three levels of reporting. For complex multi-object reports, leveraging the API and pulling into a BI tool or datawarehouse for complex reports is industry standard. For in-app reports, we can build but after going through a design workshop and understanding which reports live in-app and which are exported for more complexity. | E23: SX | G23: SX | H23: Data to be pull from NGRS | I23: 2e | J23: Y | K23: Data to be pull from NGRS | L23: n
B24: Actual Hour vs Billing hour (Banks requirement) | C24: Y | D24: All reports to be evaluated and there are three levels of reporting. For complex multi-object reports, leveraging the API and pulling into a BI tool or datawarehouse for complex reports is industry standard. For in-app reports, we can build but after going through a design workshop and understanding which reports live in-app and which are exported for more complexity. | E24: X | G24: X | H24: Data to be pull from NGRS | I24: 2e | J24: Y | K24: Data to be pull from NGRS | L24: n
B25: Allowance Report | C25: Y | D25: All reports to be evaluated and there are three levels of reporting. For complex multi-object reports, leveraging the API and pulling into a BI tool or datawarehouse for complex reports is industry standard. For in-app reports, we can build but after going through a design workshop and understanding which reports live in-app and which are exported for more complexity. | E25: SX | G25: SX | H25: Data to be pull from NGRS | I25: 2e | J25: Y | K25: Data to be pull from NGRS | L25: n
B26: Demand and constraint report | C26: Y | D26: All reports to be evaluated and there are three levels of reporting. For complex multi-object reports, leveraging the API and pulling into a BI tool or datawarehouse for complex reports is industry standard. For in-app reports, we can build but after going through a design workshop and understanding which reports live in-app and which are exported for more complexity. | E26: SX | G26: SX | H26: Data to be pull from NGRS | I26: 2e | J26: Y | K26: Data to be pull from NGRS | L26: n
B27: PLRD fee report | C27: Y | D27: All reports to be evaluated and there are three levels of reporting. For complex multi-object reports, leveraging the API and pulling into a BI tool or datawarehouse for complex reports is industry standard. For in-app reports, we can build but after going through a design workshop and understanding which reports live in-app and which are exported for more complexity. | E27: SX | G27: SX | H27: Data to be pull from NGRS | I27: 2e | J27: Y | K27: Data to be pull from NGRS | L27: n
B28: Customisable report to be able to schedule to email | C28: Y | D28: All reports to be evaluated and there are three levels of reporting. For complex multi-object reports, leveraging the API and pulling into a BI tool or datawarehouse for complex reports is industry standard. For in-app reports, we can build but after going through a design workshop and understanding which reports live in-app and which are exported for more complexity. | E28: X | G28: X | H28: Data to be pull from NGRS | I28: 2e | J28: Y | K28: Data to be pull from NGRS | L28: n
B29: Audit trial report (All transaction made within system) | C29: Y | D29: All reports to be evaluated and there are three levels of reporting. For complex multi-object reports, leveraging the API and pulling into a BI tool or datawarehouse for complex reports is industry standard. For in-app reports, we can build but after going through a design workshop and understanding which reports live in-app and which are exported for more complexity. | E29: SX | G29: SX | H29: Data to be pull from NGRS | I29: 2e | J29: Y | K29: Data to be pull from NGRS | L29: n
B30: Light duty/non-deployable report | C30: Y | D30: All reports to be evaluated and there are three levels of reporting. For complex multi-object reports, leveraging the API and pulling into a BI tool or datawarehouse for complex reports is industry standard. For in-app reports, we can build but after going through a design workshop and understanding which reports live in-app and which are exported for more complexity. | E30: X | G30: X | H30: Data to be pull from NGRS | I30: 2e | J30: Y | K30: Data to be pull from NGRS | L30: n
... B55: Sub Error Report | C55: Y | D55: All reports to be evaluated and there are three levels of reporting. For complex multi-object reports, leveraging the API and pulling into a BI tool or datawarehouse for complex reports is industry standard. For in-app reports, we can build but after going through a design workshop and understanding which reports live in-app and which are exported for more complexity. | E55: SX | G55: SX | H55: Data to be pull from NGRS | I55: 2e | J55: Y | K55: Data to be pull from NGRS | L55: n
B56: CLS Nominal Roll | C56: P | D56: All reports to be evaluated and there are three levels of reporting. For complex multi-object reports, leveraging the API and pulling into a BI tool or datawarehouse for complex reports is industry standard. For in-app reports, we can build but after going through a design workshop and understanding which reports live in-app and which are exported for more complexity. | E56: X | G56: N | I56: 2e | L56: n
B57: Lateness Report | C57: Y | D57: All reports to be evaluated and there are three levels of reporting. For complex multi-object reports, leveraging the API and pulling into a BI tool or datawarehouse for complex reports is industry standard. For in-app reports, we can build but after going through a design workshop and understanding which reports live in-app and which are exported for more complexity. | E57: SX | G57: SX | H57: Data to be pull from NGRS | I57: 2e | J57: Y | K57: Data to be pull from NGRS | L57: n
B58: Manpower EI Table | C58: P | D58: All reports to be evaluated and there are three levels of reporting. For complex multi-object reports, leveraging the API and pulling into a BI tool or datawarehouse for complex reports is industry standard. For in-app reports, we can build but after going through a design workshop and understanding which reports live in-app and which are exported for more complexity. | E58: X | G58: N | I58: 2e | L58: n
B59: Resignation/Attrition Report | C59: Y | D59: All reports to be evaluated and there are three levels of reporting. For complex multi-object reports, leveraging the API and pulling into a BI tool or datawarehouse for complex reports is industry standard. For in-app reports, we can build but after going through a design workshop and understanding which reports live in-app and which are exported for more complexity. | E59: X | G59: X | H59: Data to be pull from NGRS | I59: 2e | J59: Y | K59: Data to be pull from NGRS | L59: n
B60: Unfulfilled job report | C60: Y | D60: All reports to be evaluated and there are three levels of reporting. For complex multi-object reports, leveraging the API and pulling into a BI tool or datawarehouse for complex reports is industry standard. For in-app reports, we can build but after going through a design workshop and understanding which reports live in-app and which are exported for more complexity. | E60: SX | G60: SX | H60: Data to be pull from NGRS | I60: 2e | J60: Y | K60: Data to be pull from NGRS | L60: n
B61: Allowance Report | C61: Y | D61: All reports to be evaluated and there are three levels of reporting. For complex multi-object reports, leveraging the API and pulling into a BI tool or datawarehouse for complex reports is industry standard. For in-app reports, we can build but after going through a design workshop and understanding which reports live in-app and which are exported for more complexity. | E61: SX | G61: SX | H61: Data to be pull from NGRS | I61: 2e | J61: Y | K61: Data to be pull from NGRS | L61: n
B62: List of job/demand detail report | C62: Y | D62: All reports to be evaluated and there are three levels of reporting. For complex multi-object reports, leveraging the API and pulling into a BI tool or datawarehouse for complex reports is industry standard. For in-app reports, we can build but after going through a design workshop and understanding which reports live in-app and which are exported for more complexity. | E62: SX | G62: SX | H62: Data to be pull from NGRS | I62: 2e | J62: Y | K62: Data to be pull from NGRS | L62: n
B63: Constraint Report | C63: Y | D63: All reports to be evaluated and there are three levels of reporting. For complex multi-object reports, leveraging the API and pulling into a BI tool or datawarehouse for complex reports is industry standard. For in-app reports, we can build but after going through a design workshop and understanding which reports live in-app and which are exported for more complexity. | E63: SX | G63: SX | H63: Data to be pull from NGRS | I63: 2e | J63: Y | K63: Data to be pull from NGRS | L63: n
B64: Roster | C64: Y | D64: All reports to be evaluated and there are three levels of reporting. For complex multi-object reports, leveraging the API and pulling into a BI tool or datawarehouse for complex reports is industry standard. For in-app reports, we can build but after going through a design workshop and understanding which reports live in-app and which are exported for more complexity. | E64: SX | G64: SX | H64: Data to be pull from NGRS | I64: 2e | J64: Y | K64: Data to be pull from NGRS | L64: n
B65: Tolerance Report | C65: Y | D65: All reports to be evaluated and there are three levels of reporting. For complex multi-object reports, leveraging the API and pulling into a BI tool or datawarehouse for complex reports is industry standard. For in-app reports, we can build but after going through a design workshop and understanding which reports live in-app and which are exported for more complexity. | E65: SX | G65: SX | H65: Data to be pull from NGRS | I65: 2e | J65: Y | K65: Data to be pull from NGRS | L65: n
B66: Resourse Partner Utilisation Report | C66: P | D66: All reports to be evaluated and there are three levels of reporting. For complex multi-object reports, leveraging the API and pulling into a BI tool or datawarehouse for complex reports is industry standard. For in-app reports, we can build but after going through a design workshop and understanding which reports live in-app and which are exported for more complexity. | E66: X | G66: N | I66: 2e | L66: n
B67: Audit Trail | C67: Y | D67: All reports to be evaluated and there are three levels of reporting. For complex multi-object reports, leveraging the API and pulling into a BI tool or datawarehouse for complex reports is industry standard. For in-app reports, we can build but after going through a design workshop and understanding which reports live in-app and which are exported for more complexity. | E67: SX | G67: SX | H67: Data to be pull from NGRS | I67: 2e | J67: Y | K67: Data to be pull from NGRS | L67: n
B68: Billing Report | C68: P | D68: All reports to be evaluated and there are three levels of reporting. For complex multi-object reports, leveraging the API and pulling into a BI tool or datawarehouse for complex reports is industry standard. For in-app reports, we can build but after going through a design workshop and understanding which reports live in-app and which are exported for more complexity. | E68: X | G68: X | H68: Data to be pull from NGRS | I68: 2e | J68: Y | K68: Data to be pull from NGRS | L68: n
B69: Manpower Utilisation Report | C69: P | D69: All reports to be evaluated and there are three levels of reporting. For complex multi-object reports, leveraging the API and pulling into a BI tool or datawarehouse for complex reports is industry standard. For in-app reports, we can build but after going through a design workshop and understanding which reports live in-app and which are exported for more complexity. | E69: X | G69: X | H69: Data to be pull from NGRS | I69: 2e | J69: Y | K69: Data to be pull from NGRS | L69: n
B70: Officer detail (qualification/personal particulars) | C70: Y | D70: All reports to be evaluated and there are three levels of reporting. For complex multi-object reports, leveraging the API and pulling into a BI tool or datawarehouse for complex reports is industry standard. For in-app reports, we can build but after going through a design workshop and understanding which reports live in-app and which are exported for more complexity. | E70: SX | G70: SX | H70: Data to be pull from LTMS | I70: 2e | J70: Y | K70: Data to be pull from NGRS | L70: n
B71: Manual Attendance Adjustment Report | C71: Y | D71: All reports to be evaluated and there are three levels of reporting. For complex multi-object reports, leveraging the API and pulling into a BI tool or datawarehouse for complex reports is industry standard. For in-app reports, we can build but after going through a design workshop and understanding which reports live in-app and which are exported for more complexity. | E71: SX | G71: SX | H71: Data to be pull from NGRS | I71: 2e | J71: Y | K71: Data to be pull from NGRS | L71: n
B72: Attendance Error Report | C72: Y | D72: All reports to be evaluated and there are three levels of reporting. For complex multi-object reports, leveraging the API and pulling into a BI tool or datawarehouse for complex reports is industry standard. For in-app reports, we can build but after going through a design workshop and understanding which reports live in-app and which are exported for more complexity. | E72: X | G72: X | H72: Data to be pull from NGRS | I72: 2e | J72: Y | K72: Data to be pull from NGRS | L72: n
B73: Officer with no status Report | C73: Y | D73: All reports to be evaluated and there are three levels of reporting. For complex multi-object reports, leveraging the API and pulling into a BI tool or datawarehouse for complex reports is industry standard. For in-app reports, we can build but after going through a design workshop and understanding which reports live in-app and which are exported for more complexity. | E73: SX | G73: SX | H73: Data to be pull from NGRS | I73: 2e | J73: Y | K73: Data to be pull from NGRS | L73: n
B74: Time Attendance Discrepancies report (Clock In Vs Payable) | C74: Y | D74: All reports to be evaluated and there are three levels of reporting. For complex multi-object reports, leveraging the API and pulling into a BI tool or datawarehouse for complex reports is industry standard. For in-app reports, we can build but after going through a design workshop and understanding which reports live in-app and which are exported for more complexity. | E74: SX | G74: SX | H74: Data to be pull from NGRS | I74: 2e | J74: Y | K74: Data to be pull from NGRS | L74: n
B75: List of Data to perform Audit (i.e. manual adjsutment to attendance) | C75: Y | D75: All reports to be evaluated and there are three levels of reporting. For complex multi-object reports, leveraging the API and pulling into a BI tool or datawarehouse for complex reports is industry standard. For in-app reports, we can build but after going through a design workshop and understanding which reports live in-app and which are exported for more complexity. | E75: SX | G75: SX | H75: Data to be pull from NGRS | I75: 2e | J75: Y | K75: Data to be pull from NGRS | L75: n
B76: SMRT Manpower Status Report | C76: P | D76: All reports to be evaluated and there are three levels of reporting. For complex multi-object reports, leveraging the API and pulling into a BI tool or datawarehouse for complex reports is industry standard. For in-app reports, we can build but after going through a design workshop and understanding which reports live in-app and which are exported for more complexity. | E76: X | G76: N | I76: 2e | L76: n
F110: Cathy - can you think how we might do this? The employee could be linked to an agency/contractor using a UDF or home location etc… but per scenario above, if they belong to 2 contractors.. Can we still somehow report which contractor rostered them to the shift? Actual hours worked will be costed per client per contractor. Should be no issues with this requirement.

Sheet 3a. Security
A1: 3a. | B1: Security. In terms of software and infrastructure security, the Software service provider shall: | C1: Fulfil Certis' Requirements? (Yes/No/Partial) | D1: Remarks | E1: SG (X if required SX Showstopper) | F1: AU (X if required) | G1: Revised Requirements | H1: Certis Remarks | I1: Indicator | J1: Response (Yes/No/Partial) | K1: Remarks | L1: Cadence Related
A2: i. | B2: Data Encryption. All data transmitted over public networks and stored in databases must be encrypted using industry-standard protocols. | C2: Y | E2: SX | F2: X | G2: SX | H2: No Change | I2: 3a | J2: Y | L2: n
A3: ii. | B3: Access Control. Role-based access control (RBAC) to ensure users can only access data and functionalities relevant to their role. | C3: Y | E3: SX | F3: X | G3: SX | H3: No Change | I3: 3a | J3: Y | L3: n
A4: iii. | B4: Audit Trails. Comprehensive logging of user actions and system changes for audit purposes, with logs stored securely for a minimum of 1 year. | C4: Y | E4: SX | F4: X | G4: SX | H4: No Change | I4: 3a | J4: Y | L4: n
A5: iv. | B5: Notifications. Ability to generate real time alert notifications for critical security situations. | C5: Y | E5: SX | F5: X | G5: SX | H5: No Change | I5: 3a | J5: Y | L5: n
A6: v. | B6: Track record. State if you have had a security or data breach in the last 5 years. | C6: Y | E6: SX | F6: X | G6: SX | H6: No Change | I6: 3a | J6: Y | L6: n
A7: vi. | B7: Provide additional information in the Vendor Risk Assessment Questionnaire, to be sent separately. | C7: Y | E7: SX | F7: X | G7: SX | H7: No Change | I7: 3a | J7: Y | L7: n
F113: Cathy - can you think how we might do this? The employee could be linked to an agency/contractor using a UDF or home location etc… but per scenario above, if they belong to 2 contractors.. Can we still somehow report which contractor rostered them to the shift? Actual hours worked will be costed per client per contractor. Should be no issues with this requirement.

Sheet 3b. User Interface and User Exp
A1: 3b. | B1: User Interface and User Experience. The Software service provider shall: | C1: Fulfil Certis' Requirements? (Yes/No/Partial) | D1: Remarks | E1: SG (X if required SX Showstopper) | F1: AU (X if required) | G1: Revised Requirements | H1: Certis Remarks | I1: Indicator | J1: Response (Yes/No/Partial) | K1: Remarks | L1: Cadence Related
A2: i. | B2: User Interface. Offer an intuitive and user-friendly interface, accessible to users with varying levels of technical proficiency. | C2: Y | E2: X | F2: X | G2: X | H2: No Change | I2: 3b | J2: Y | L2: n
B3: Adopt industry best practices for UI/UX (with particular emphasis on ISO 9241-210 2019). | C3: Y | E3: X | F3: X | G3: X | H3: No Change | I3: 3b | J3: Y | L3: n
B4: Be accessible from a range of common computing devices (e.g. Mac, PC, Apple and Android mobile devices). | C4: Y | E4: SX | F4: X | G4: SX | H4: No Change | I4: 3b | J4: Y | L4: n
B5: Supports Modern Web Browsers (Chrome, Safari, Edge, Samsung Internet, Firefox) | C5: Y | E5: SX | F5: X | G5: SX | H5: No Change | I5: 3b | J5: Y | L5: n
A6: ii. | B6: Localisation.
B7: Language - Support English and Mandarin and Traditional Mandarin language interfaces, documentation and support (e.g. language spoken with agents in call centre). | C7: Y | E7: X | F7: X | G7: X | H7: No Change | I7: 3b | J7: Y | L7: n
B8: Date/Time - Support daylight saving time. | C8: Y | E8: X | F8: X | G8: X | H8: No Change | I8: 3b | J8: Y | L8: n
B9: Currencies – Support multiple currencies and handle currency conversions (e.g. to calculate cost) | C9: Y | E9: X | F9: X | G9: X | H9: No Change | I9: 3b | J9: Y | L9: n
F113: Cathy - can you think how we might do this? The employee could be linked to an agency/contractor using a UDF or home location etc… but per scenario above, if they belong to 2 contractors.. Can we still somehow report which contractor rostered them to the shift? Actual hours worked will be costed per client per contractor. Should be no issues with this requirement.

Sheet 3c. Performance-Scalability
A1: 3c. | B1: Performance and Scalability. The Software service provider shall: | C1: Fulfil Certis' Requirements? (Yes/No/Partial) | D1: Remarks | E1: SG (X if required SX Showstopper) | F1: AU (X if required) | G1: Revised Requirements | H1: Certis Remarks | I1: Indicator | J1: Response (Yes/No/Partial) | K1: Remarks | L1: Cadence Related
A2: i. | B2: Response Time. For web-based applications, align to industry best practices. The provider may reference Google Core Web Vitals metrics | C2: Y | E2: X | F2: X | G2: X | H2: No Change | I2: 3c | J2: Y | L2: n
B3: 1. Loading Performance – Largest Contentful Paint (LCP) time of 2.5 seconds or less. | C3: Y | E3: X | F3: X | G3: X | H3: No Change | I3: 3c | J3: Y | L3: n
B4: 2. Interactivity – First Input Delay (FID) of 100 milliseconds or less. | C4: Y | E4: X | F4: X | G4: X | H4: No Change | I4: 3c | J4: Y | L4: n
B5: 3. Stability – Cumulative Layout Shift (CLS) score of 0.1 or less. | C5: Y | E5: X | F5: X | G5: X | H5: No Change | I5: 3c | J5: Y | L5: n
A6: ii. | B6: Throughput. The system must support simultaneous access for up to 20,000 users without performance degradation. | C6: Y | E6: X | F6: X | G6: X | H6: No Change | I6: 3c | J6: Y | L6: n
A7: iii. | B7: Scalability: The system should be scalable to accommodate future growth in user numbers, tenants and associated data volume without any disruption to user services or degradation in performance. | C7: Y | E7: X | F7: X | G7: X | H7: No Change | I7: 3c | J7: Y | L7: n
F113: Cathy - can you think how we might do this? The employee could be linked to an agency/contractor using a UDF or home location etc… but per scenario above, if they belong to 2 contractors.. Can we still somehow report which contractor rostered them to the shift? Actual hours worked will be costed per client per contractor. Should be no issues with this requirement.

Sheet 3d. Support-Maintenance
A1: 3d. | B1: Support and Maintenance. The Software service provider shall: | C1: Fulfil Certis' Requirements? (Yes/No/Partial) | D1: Remarks | E1: SG (X if required SX Showstopper) | F1: AU (X if required) | G1: Revised Requirements | H1: Certis Remarks | I1: Indicator | J1: Response (Yes/No/Partial) | K1: Remarks | L1: Cadence Related
A2: i. | B2: Technical Support. Provide in-house technical support that is NOT out-sourced to a third party and is available 24/7, ensuring priority response to critical issues (maximum 15mins response time) and their resolution within 6 hours. The technical support team must be contactable via a toll-free phone number . All other issues must be reolved within 12 hours upon submission of request. Online Chat support to respond to non-critical queries is optional. | C2: Y | D2: Detailed response sent by email. | E2: SX | F2: X | G2: SX | H2: No change | I2: 3d | J2: Y | L2: n
A3: ii. | B3: Documentation. Comprehensive and up-to-date documentation, including user manuals, installation guides, and troubleshooting tips, available 24/7. | C3: Y | E3: SX | F3: X | G3: SX | H3: No change | I3: 3d | J3: Y | L3: n
A4: iii. | B4: Software Updates. Regular updates and patches to address security vulnerabilities, bugs, and enhance functionality. | C4: Y | E4: SX | F4: X | G4: SX | H4: No change | I4: 3d | J4: Y | L4: n
A5: iv. | B5: Align to maintenance standards. Be governed by a comprehensive software lifecycle strategy, strongly aligning to ISO/IEC/IEEE 12207:2017. | C5: Y | E5: X | F5: X | G5: X | H5: No change | I5: 3d | J5: Y | L5: n
A6: v. | B6: The System must provide a well-defined exit strategy to ensure a seamless transition in case of contract termination, migration to another system, or vendor replacement. The exit process should be transparent, structured, and minimize operational disruptions. | C6: Y | E6: X | F6: X | G6: X | H6: No change | I6: 3d | J6: Y | L6: n
B7: User Manual/ Training & Processes | C7: Fulfil Certis' Requirements? (Yes/No/Partial) | D7: Remarks
A8: i | B8: The vendor should provide user manual & Training for the system and its subsystems' functions within the NGRS system. | C8: Y | E8: SX | G8: SX | H8: No change | I8: 3d | J8: Y | L8: n
A9: ii | B9: The vendor should provide an end-to-end process for each function within the NGRS system. | C9: Y | E9: SX | G9: SX | H9: No change | I9: 3d | J9: Y | L9: n
F113: Cathy - can you think how we might do this? The employee could be linked to an agency/contractor using a UDF or home location etc… but per scenario above, if they belong to 2 contractors.. Can we still somehow report which contractor rostered them to the shift? Actual hours worked will be costed per client per contractor. Should be no issues with this requirement.

Sheet 3e. Reliability-Availability
A1: 3e. | B1: Reliability and Availability. The Software service provider shall: | C1: Fulfil Certis' Requirements? (Yes/No/Partial) | D1: Remarks | E1: SG (X if required SX Showstopper) | F1: AU (X if required) | G1: Revised Requirements | H1: Certis Remarks | I1: Indicator | J1: Response (Yes/No/Partial) | K1: Remarks | L1: Cadence Related
A2: i. | B2: System availability. Ensure that the Software is available 24hrs, 7 days a week and all year-round, and has an availability of 99.7%, including planned maintenance periods, which shall be designed to have minimum impact to users (takes place in off-peak hours) and be informed to Certis in advance. | C2: Y | E2: SX | F2: X | G2: SX | H2: No Change | I2: 3e | J2: Y | L2: n
A3: ii. | B3: Data Backup. Maintains at least two levels of backup and failover production. Automated daily backups of all data, with the ability to perform additional backups on demand, plus a Recovery Point Objective (RPO) of 15mins. | C3: Y | D3: Detailed response sent by email. | E3: X | F3: X | G3: X | H3: No Change | I3: 3e | J3: Y | L3: n
A4: iii. | B4: System Recovery. The system should ensure the recovery time (RTO) is within 4 hours after services offline or upon notification by Certis, whichever is earlier. | C4: Y | E4: X | F4: X | G4: X | H4: No Change | I4: 3e | J4: Y | L4: n
A5: iv. | B5: Offline Mode. Demonstrate capability for critical functions of the system to continue to function while user device is offline. | C5: Y | D5: Detailed response sent by email. Part of short-term roadmap. | E5: X | F5: X | G5: X | H5: No Change | I5: 3e | J5: Y | L5: n
B6: The tenderer shall provide a report to Certis within 48 hours upon notification of service disruption, to detail the possible root issues and preventative solution of the incident | C6: Y | E6: X | F6: X | G6: X | H6: No Change | I6: 3e | J6: Y | L6: n
B7: BCP | C7: Fulfil Certis' Requirements? (Yes/No/Partial) | D7: Remarks
A8: i. | B8: The vendor should provide information on the planned downtime schedule for the system | C8: Y | E8: SX | G8: SX | H8: No Change | I8: 3e | J8: Y | L8: n
A9: ii | B9: The vendor should provide a Business Continuity Plan (BCP) for unplanned downtime, as several critical systems rely on NGRS system data for our daily operations | C9: Y | E9: SX | G9: SX | H9: No Change | I9: 3e | J9: Y | L9: n
A10: iii. | B10: The vendor should advise on how users can extract the roster from NGRS when the system is down, so it can be referenced for withdrawing arm demand, such as drawing of arms | C10: Y | E10: SX | G10: SX | H10: No Change | I10: 3e | J10: Y | L10: n
F113: Cathy - can you think how we might do this? The employee could be linked to an agency/contractor using a UDF or home location etc… but per scenario above, if they belong to 2 contractors.. Can we still somehow report which contractor rostered them to the shift? Actual hours worked will be costed per client per contractor. Should be no issues with this requirement.

Sheet 3f. Integration
A1: 3f. | B1: Integration. The Software service provider shall: | C1: Fulfil Certis' Requirements? (Yes/No/Partial) | D1: Remarks | E1: SG (X if required SX Showstopper) | F1: AU (X if required) | G1: Revised Requirements | H1: Certis Remarks | I1: Indicator | J1: Response (Yes/No/Partial) | K1: Remarks | L1: Cadence Related
A2: i.a | B2: APIs. The system must provide robust application programming interfaces (APIs) for integration with existing Certis systems (e.g. Time Attendance) | C2: Y | E2: SX | F2: X | G2: SX | H2: No Change | I2: 3f | J2: Y
A3: i.b | B3: Please supply a full list of your API catalogue available for integration, with business and technical definitions, and what operational process they support | C3: Y | E3: SX | F3: X | G3: SX | H3: No Change | I3: 3f | J3: Y
A4: ii. | B4: SSO. Support various types of SSO authorisation protocols does your Software support (e.g. OAuth 2.0/JWT/SAML 2.0). List the types supported. | C4: Y | E4: SX | F4: X | G4: SX | H4: No Change | I4: 3f | J4: Y
A5: iii. | B5: Data Import/Export. Data Import/Export: Facilities to easily import and export data in standard formats (CSV, XML, etc.) for interoperability with other systems. | C5: Y | E5: X | F5: X | G5: X | H5: No Change | I5: 3f | J5: Y
A6: iv. | B6: The solution must natively support or provide comprehensive and well documented APIs to enable seamless integration with Certis' core business systems, including SAP S/4HANA, SAP SuccessFactors Employee Central, SAP Employee Central Payroll, and Tableau. | C6: Y | E6: SX | F6: X | G6: SX | H6: No Change | I6: 3f | J6: Y
A7: v. | B7: Interoperability. The system must use standard data exchange formats (e.g., JSON, XML) to ensure interoperability with a variety of software systems and technologies. | C7: Y | E7: SX | F7: X | G7: SX | H7: No Change | I7: 3f | J7: Y
A8: vi. | B8: The vendor must present a software architecture diagram that clearly illustrates integration points with the following systems:: | C8: Y | E8: X | F8: X | G8: X | H8: No Change | I8: 3f | J8: Y
B9: SAP S/4HANA – for the exchange of master data, including clients, sites, sales orders, purchase orders, and resource demand, emp data, SAP SuccessFactors Employee Central – for syncing employee and contractor data such as personal details, licenses, accreditations, and training records. SAP Employee Central Payroll – for transmitting validated timesheet data to support payroll processing. Frontline Time and Attendance Application – for the ingestion of attendance data, including check-in/out times, geolocation, and facial verification. | C9: Y | E9: SX | F9: X | G9: SX | H9: No Change | I9: 3f | J9: Y
B10: (b) 3rd party system to create and fill rosters (with data from NGRS) | C10: Y | E10: X | F10: X | G10: X | H10: No Change | I10: 3f | J10: Y
B11: (c) 3rd party system for Employee Time Attendance | C11: Y | E11: SX | F11: X | G11: SX | H11: No Change | I11: 3f | J11: Y | L11: n
B12: (d) 3rd party system for Employee shift management (view roster, shift acceptance, shift swap, shift bidding, unavailability) | C12: Y | E12: X | F12: X | G12: X | H12: No Change | I12: 3f | J12: Y | L12: n
B13: To avoid scheduling conflicts, operations and training schedules must be automatically deconflicted. The LMS and TMS will send course enrolment, cancellation, and amendment details—including training hours—to the Rostering system the same as to be updated in Rostering as training for officer. Likewise, the rostering system must be able to send course cancellation requests from the Rostering system to LMS/TMS when Operations decides to withdraw employees from scheduled courses due to manpower shortages. When a learner is enrolled in one of these designated courses, the LMS/TMS will send both the training hours and the learner’s completion status to the Rostering system, the same as to store in Rostering system and use for optimual rostering. Training hours are essential for the Rostering system to calculate total monthly working hours and ensure compliance with statutory working time regulations. Completion status is critical for determining whether an employee is eligible to be assigned to specific duties or operational demands, based on required training constraints | C13: Y | E13: SX | G13: SX | H13: No Change | I13: 3f | J13: Y | L13: n
B14: Business Requirements added (SG BUs) | L14: n
B15: The system should be capable of integrating with our existing systems (API-enabled), such as Pre-boarding and TITUS, to sync with AEMS and NGRS. All systems should be linked to NGRS. Existing Certis Systems: SuccessFactor TITUS AEMS Allegro Argus Optimax Certis Forms e-Jobcard Cadence eCSDS RCMS At-Once ePARC | C15: Y | E15: SX | G15: SX | H15: No Change | I15: 3f | J15: Y | L15: n
B16: External System Integration: The system need to integrate with external systems to push and pull data, and assign tasks to the correct demand if automatic team formation is not feasible. | C16: Y | E16: SX | G16: SX | H16: No Change | I16: 3f | J16: Y | L16: n
B17: Synchronisation | C17: Fulfil Certis' Requirements? (Yes/No/Partial) | D17: Remarks
A18: i | B18: Real Time Synchronizing Function Real Time Sync Button to push data from/to NGRS (any creation/changes/adjustment made in either of the platforms, sync button to facilitate the immediate update between the systems) i. Cadence ii. Ejobcard iii. Attendance to SAP iv. Titus v. Qualification from SAP vi. Posting from SAP vii. AEMS viii.AtOnce Ix. RCMS (Resource Contractor Management System) X. Eparcs Xi. Allegro Xii. TATS (Transport Attendance Tracking System) Sensemaking | C18: Y | E18: SX | G18: SX | H18: No Change | I18: 3f | J18: Y | L18: n
B19: ARGUS/or deployment Dashboard Others (Ensuring scalability for future systems) | C19: Y | E19: SX | G19: SX | H19: No Change | I19: 3f | J19: Y | L19: n
B20: Tracking of LD for outcome based contracts | C20: P | D20: To be evaluated. | E20: X | G20: N | H20: Not Required | I20: 3f

Sheet 3g. Configurability
A1: 3g. | B1: Configurability and adaptability. The Software service provider shall: | C1: Fulfil Certis' Requirements? (Yes/No/Partial) | D1: Remarks | E1: SG (X if required SX Showstopper) | F1: AU (X if required) | G1: Revised Requirements | H1: Certis Remarks | I1: Indicator | J1: Response (Yes/No/Partial) | K1: Remarks | L1: Cadence Related
A2: i. | B2: Flexible Configuration. Offer extensive configuration options to adapt to Certis’ specific scheduling, compliance, and reporting needs without requiring custom coding. | C2: Y | E2: SX | F2: X | G2: SX | H2: No Change | I2: 3g | J2: Y | L2: n
A3: ii | B3: User-defined Rules. Ability for users to define and modify scheduling rules, compliance checks, and notification settings within the system’s interface. | C3: Y | E3: SX | F3: X | G3: SX | H3: No Change | I3: 3g | J3: Y | L3: n
A4: iii. | B4: Adaptation to New Business Scenarios. The system must be designed to easily accommodate new business scenarios, such as changes in workforce size, shift patterns, or compliance requirements, with minimal system modification. | C4: Y | E4: SX | F4: X | G4: SX | H4: No Change | I4: 3g | J4: Y | L4: n
A5: iv. | B5: Modular Design. Preferably, the system should have a modular design, allowing Certis to add or update modules as needed without affecting the overall system integrity. | C5: Y | E5: X | F5: X | G5: X | H5: No Change | I5: 3g | J5: Y | L5: n

Sheet 3h. Compliance
A1: 3h. | B1: Compliance to Data Standards and Policies. The Software service provider shall demonstrate: | C1: Fulfil Certis' Requirements? (Yes/No/Partial) | D1: Remarks | E1: SG (X if required SX Showstopper) | F1: AU (X if required) | G1: Revised Requirements | H1: Certis Remarks | I1: Indicator | J1: Response (Yes/No/Partial) | K1: Remarks | L1: Cadence Related
A2: i. | B2: Legal Compliance. Your software complies with international and local data protection regulations (e.g., GDPR, HIPAA, PDPA, etc.) | C2: Y | E2: SX | F2: X | G2: SX | H2: No Change | I2: 3h | J2: Y | L2: n
A3: ii. | B3: Data Privacy Laws. Compliance with data protection laws relevant to the regions in which the platform operates. | C3: Y | E3: SX | F3: X | G3: SX | H3: No Change | I3: 3h | J3: Y | L3: n
A4: iii | B4: Data Isolation. ability to isolate data access and data storage in Australia and Singapore, while maintaining data centres in each country. | C4: Y | E4: X | F4: X | G4: X | H4: No Change | I4: 3h | J4: Y | L4: n
A5: iv. | B5: Compliance with Certis data-related policies. These documents will be forwarded separately to the vendor for consideration. (to delete) | C5: Y | E5: X | F5: X | G5: X | H5: No Change | I5: 3h | J5: Y | L5: n
B6: Business Requirements added (SG BUs)
B7: The system should be able to manage consent for changing off days to workdays, such as overrides in NGRS (subjective) and rostering change management. | C7: Y | E7: X | G7: X | H7: No Change | I7: 3h | J7: Y | L7: n
B8: The system must accommodate regulatory requirements, including the tracking of monthly overtime hours, daily max hour, consecutive working day, rest hour in between shift, max hour consecutive workind day for part timer within a week, Licenses - PLRD, RTT, PGPS, PABP, AO, Arm monitoring, | C8: Y | E8: SX | G8: SX | H8: No Change | I8: 3h | J8: Y | L8: n
B9: Configuration and business rule by business/product type/employee group | C9: Y | E9: SX | G9: SX | H9: No Change | I9: 3h | J9: Y | L9: n
